Workbook

Sheet top&core医院DDD
A1: 疼痛试点医院 焦虑医院试点医院 | Q1: 与瞄准镜保持一致 | AM1: 注意合规表述
A2: 医院 | B2: 医院级别 | C2: DM | D2: MICS | E2: 准入标签 | F2: 是否有进货金额限制 | G2: 限制金额 | H2: 院内渠道开放情况 | I2: 3月tth预估实际 | J2: 4月tth预估实际 | K2: 5月tth预估实际 | L2: 6月tth预估实际 | M2: 7月tth预估实际 | N2: 8月tth预估实际 | O2: 梯队标签 | P2: 月销量变化 | Q2: 头痛门诊/周 | R2: 头痛客户数 | S2: 眩晕门诊/周 | T2: 眩晕门诊客户数 | U2: 标签客户数 | V2: 目标活跃客户数 | W2: 活跃客户数 | X2: A客户 | Y2: B客户 | Z2: C客户 | AA2: D客户 | AB2: A客户贡献占比 | AC2: B客户贡献占比 | AD2: C客户贡献占比 | AE2: D客户贡献占比 | AF2: 阶梯治疗 | AG2: 止痛优选 | AH2: 短期治痛 | AI2: 治痛管理 | AJ2: 资深治痛管理 | AK2: 治痛管理大师 | AL2: Q4目标月均梯队医院 | AM2: 9月TTH目标 | AN2: 目标A客户贡献预估 | AO2: 目标B客户贡献预估 | AP2: 目标C客户贡献预估 | AQ2: 目标D客户贡献预估 | AR2: 洞察诊断 | AS2: 策略 | AT2: 针对各策略下客户增长及增长机会的具体行动计划 | AU2: 所需需求&支持
A3: 江苏省人民医院 | B3: TOP | C3: 孟鈃 | D3: 王方方/芦晓辉 | E3: his直连药店 | F3: 不适用 | I3: 1124 | J3: 1208 | K3: 1204 | L3: 1184 | M3: 1476 | O3: 1000+ | Q3: 3 | R3: 3 | S3: 2 | T3: 2 | U3: 20 | V3: 20 | W3: 16 | X3: 3 | Y3: 7 | Z3: 6 | AA3: 0 | AB3: =IFERROR(SUMIFS('top&core医院客户DDD'!$R$4:$R$557,'top&core医院客户DDD'!$A$4:$A$557,$A3,'top&core医院客户DDD'!$F$4:$F$557,LEFT(AB$2,1))/SUMIFS('top&core医院客户DDD'!$R$4:$R$557,'top&core医院客户DDD'!$A$4:$A$557,$A3),"") -> 0.11382114 | AC3: =IFERROR(SUMIFS('top&core医院客户DDD'!$R$4:$R$557,'top&core医院客户DDD'!$A$4:$A$557,$A3,'top&core医院客户DDD'!$F$4:$F$557,LEFT(AC$2,1))/SUMIFS('top&core医院客户DDD'!$R$4:$R$557,'top&core医院客户DDD'!$A$4:$A$557,$A3),"") -> 0.056910569 | AD3: =IFERROR(SUMIFS('top&core医院客户DDD'!$R$4:$R$557,'top&core医院客户DDD'!$A$4:$A$557,$A3,'top&core医院客户DDD'!$F$4:$F$557,LEFT(AD$2,1))/SUMIFS('top&core医院客户DDD'!$R$4:$R$557,'top&core医院客户DDD'!$A$4:$A$557,$A3),"") -> 0.82926829 | AE3: =IFERROR(SUMIFS('top&core医院客户DDD'!$R$4:$R$557,'top&core医院客户DDD'!$A$4:$A$557,$A3,'top&core医院客户DDD'!$F$4:$F$557,LEFT(AE$2,1))/SUMIFS('top&core医院客户DDD'!$R$4:$R$557,'top&core医院客户DDD'!$A$4:$A$557,$A3),"") -> 0 | AF3: 10 | AG3: 3 | AH3: 0 | AI3: 1 | AJ3: 0 | AK3: 2 | AL3: 1500+ | AM3: 1500 | AN3: 700 | AO3: 200 | AP3: 500 | AQ3: 100 | AR3: 1、超代客户不稳定 2、客户面拓展需扩大 | AS3: 1、超代客户通过系列会议和学科培养稳定产出 2、分科室全面拓展，开发新客户 | AT3: 1. 针对存量超代客户，通过靶握周三会议与分层管理，保障业绩持续稳定产出。 2. 针对增量市场，落实分科室全域拓展策略，开发新客户，实现客户规模与整体业务增量突破。 | AU3: 靶握周三会议、头痛病例集
A4: 苏州大学附属第一医院 | B4: TOP | C4: 何方禹 | D4: 张桂香/陈利丰 | E4: 未准入 | F4: 不适用 | G4: 不适用 | H4: 不适用 | I4: 1086 | J4: 1048 | K4: 908 | L4: 1164 | M4: 1260 | O4: 1000+ | Q4: 3 | R4: 2 | S4: 2 | T4: 5 | U4: 17 | V4: 20 | W4: 13 | X4: 2 | Y4: 10 | Z4: 1 | AA4: 0 | AB4: =IFERROR(SUMIFS('top&core医院客户DDD'!$R$4:$R$557,'top&core医院客户DDD'!$A$4:$A$557,$A4,'top&core医院客户DDD'!$F$4:$F$557,LEFT(AB$2,1))/SUMIFS('top&core医院客户DDD'!$R$4:$R$557,'top&core医院客户DDD'!$A$4:$A$557,$A4),"") -> 0.65923567 | AC4: =IFERROR(SUMIFS('top&core医院客户DDD'!$R$4:$R$557,'top&core医院客户DDD'!$A$4:$A$557,$A4,'top&core医院客户DDD'!$F$4:$F$557,LEFT(AC$2,1))/SUMIFS('top&core医院客户DDD'!$R$4:$R$557,'top&core医院客户DDD'!$A$4:$A$557,$A4),"") -> 0.054140127 | AD4: =IFERROR(SUMIFS('top&core医院客户DDD'!$R$4:$R$557,'top&core医院客户DDD'!$A$4:$A$557,$A4,'top&core医院客户DDD'!$F$4:$F$557,LEFT(AD$2,1))/SUMIFS('top&core医院客户DDD'!$R$4:$R$557,'top&core医院客户DDD'!$A$4:$A$557,$A4),"") -> 0.2866242 | AE4: =IFERROR(SUMIFS('top&core医院客户DDD'!$R$4:$R$557,'top&core医院客户DDD'!$A$4:$A$557,$A4,'top&core医院客户DDD'!$F$4:$F$557,LEFT(AE$2,1))/SUMIFS('top&core医院客户DDD'!$R$4:$R$557,'top&core医院客户DDD'!$A$4:$A$557,$A4),"") -> 0 | AF4: 11 | AG4: 0 | AH4: 0 | AI4: 0 | AJ4: 1 | AK4: 1 | AL4: 1500+ | AM4: 1900 | AN4: 1080 | AO4: 180 | AP4: 636 | AQ4: 4 | AR4: 1、TTH预估高度集中（赵&王），4+4客户不足; 2、B类客户诊断率低和推荐率低，无法推动正反馈持续使用经验； 3、C类客户诊断率低，对于VM认知不足，需快速突破。 | AS4: 深做AC 快拓BD | AT4: 1、深做AC，A类客户：赵hr（治痛管理大师）持续提升；张qq（目标：治痛管理）提升推荐率和DOT，做好患者随访提升复购率，C类客户：王dp（治痛管理大师）做好患者随访提升复购率；于亚峰（目标：治痛管理）提升诊断率在VM和p-VM的患者上推荐使用，DOT3-6月的治疗周期，小C潘晨（目标：止痛优选）&陶朵朵（目标：止痛优选）&郭燕（目标：止痛优选）提升诊断率和推荐率。 2、快拓B类客户：高潜力痛晕客户，实现止痛优选（薛sr、陈zg、王h、段xy、倪jq、高hq），持续推动提升诊断率和DOT; 3、同步拓展神外：头痛潜力客户：陈zq（目标：止痛优选） | AU4: 1、平台与讲者：标杆医生区域讲者机会，学术会议搭建 2、跨科联动：神内头痛中心-耳鼻喉眩晕-疼痛科多学科联动活动 3、准入与渠道：推动进院/临时采购或外配流转，打通处方最后一公里；
A5: 南京鼓楼医院 | B5: TOP | C5: 孟鈃 | D5: 罗世懿/李雪茹 | E5: 正式准入 | F5: 否 | H5: 仅限神经内科 | I5: 932 | J5: 952 | K5: 952 | L5: 964 | M5: 1204 | O5: 1000+ | Q5: 10 | R5: 3 | S5: 5 | T5: 6 | U5: 9 | V5: 20 | W5: 13 | X5: 4 | Y5: 7 | Z5: 0 | AA5: 2 | AB5: =IFERROR(SUMIFS('top&core医院客户DDD'!$R$4:$R$557,'top&core医院客户DDD'!$A$4:$A$557,$A5,'top&core医院客户DDD'!$F$4:$F$557,LEFT(AB$2,1))/SUMIFS('top&core医院客户DDD'!$R$4:$R$557,'top&core医院客户DDD'!$A$4:$A$557,$A5),"") -> 0.77740864 | AC5: =IFERROR(SUMIFS('top&core医院客户DDD'!$R$4:$R$557,'top&core医院客户DDD'!$A$4:$A$557,$A5,'top&core医院客户DDD'!$F$4:$F$557,LEFT(AC$2,1))/SUMIFS('top&core医院客户DDD'!$R$4:$R$557,'top&core医院客户DDD'!$A$4:$A$557,$A5),"") -> 0.10963455 | AD5: =IFERROR(SUMIFS('top&core医院客户DDD'!$R$4:$R$557,'top&core医院客户DDD'!$A$4:$A$557,$A5,'top&core医院客户DDD'!$F$4:$F$557,LEFT(AD$2,1))/SUMIFS('top&core医院客户DDD'!$R$4:$R$557,'top&core医院客户DDD'!$A$4:$A$557,$A5),"") -> 0.0099667774 | AE5: =IFERROR(SUMIFS('top&core医院客户DDD'!$R$4:$R$557,'top&core医院客户DDD'!$A$4:$A$557,$A5,'top&core医院客户DDD'!$F$4:$F$557,LEFT(AE$2,1))/SUMIFS('top&core医院客户DDD'!$R$4:$R$557,'top&core医院客户DDD'!$A$4:$A$557,$A5),"") -> 0.10299003 | AF5: 7 | AG5: 2 | AH5: 2 | AI5: 1 | AJ5: 0 | AK5: 1 | AL5: 2000+ | AM5: 1820 | AN5: 1130 | AO5: 330 | AP5: 100 | AQ5: 260 | AR5: 大A承担大部分产出， 其余断层严重；B和C客户薄弱；D正在崛起 | AS5: 建立以大A为核心的mdt 多学科头痛团队，院内资源合理化分配和利用；使得头痛患者在任何科室都不流失 | AT5: 1.头痛中心建立后的质控建设； 2以清秀主任为核心的三方会交流、以孟老师为核心的mdtLB交流团结中青年；3.多学科互相流通；4.江北转诊机制 | AU5: 清秀主任全国平台打造
A6: 山东第一医科大学附属省立医院 | B6: TOP | C6: 李路 | D6: 王明月/白云松 | E6: 正式准入 | F6: 否 | H6: 仅限门诊处方，病房未开通 | I6: 931 | J6: 1024 | K6: 906 | L6: 933 | M6: 1144 | O6: 1000+ | Q6: 1.5 | R6: 2 | S6: 3 | T6: 9 | U6: 32 | V6: 30 | W6: 22 | X6: 3 | Y6: 10 | Z6: 5 | AA6: 4 | AB6: =IFERROR(SUMIFS('top&core医院客户DDD'!$R$4:$R$557,'top&core医院客户DDD'!$A$4:$A$557,$A6,'top&core医院客户DDD'!$F$4:$F$557,LEFT(AB$2,1))/SUMIFS('top&core医院客户DDD'!$R$4:$R$557,'top&core医院客户DDD'!$A$4:$A$557,$A6),"") -> 0.06360424 | AC6: =IFERROR(SUMIFS('top&core医院客户DDD'!$R$4:$R$557,'top&core医院客户DDD'!$A$4:$A$557,$A6,'top&core医院客户DDD'!$F$4:$F$557,LEFT(AC$2,1))/SUMIFS('top&core医院客户DDD'!$R$4:$R$557,'top&core医院客户DDD'!$A$4:$A$557,$A6),"") -> 0.73498233 | AD6: =IFERROR(SUMIFS('top&core医院客户DDD'!$R$4:$R$557,'top&core医院客户DDD'!$A$4:$A$557,$A6,'top&core医院客户DDD'!$F$4:$F$557,LEFT(AD$2,1))/SUMIFS('top&core医院客户DDD'!$R$4:$R$557,'top&core医院客户DDD'!$A$4:$A$557,$A6),"") -> 0.14840989 | AE6: =IFERROR(SUMIFS('top&core医院客户DDD'!$R$4:$R$557,'top&core医院客户DDD'!$A$4:$A$557,$A6,'top&core医院客户DDD'!$F$4:$F$557,LEFT(AE$2,1))/SUMIFS('top&core医院客户DDD'!$R$4:$R$557,'top&core医院客户DDD'!$A$4:$A$557,$A6),"") -> 0.053003534 | AF6: 10 | AG6: 6 | AH6: 4 | AI6: 2 | AJ6: 0 | AK6: 0 | AL6: 1500+ | AM6: 1586 | AN6: 150 | AO6: 996 | AP6: 332 | AQ6: 108 | AR6: 1、新A新增头痛门诊患者归拢率低； 2、B转A，观念进展缓慢； 3、C、D客户观念升级缓慢。 | AS6: 1、通过头痛小站、GD提升患者归拢率； 2、积累正反馈病例，创造分享机会； 3、通过讲师团强化观念，MDT会议加强融动。 | AT6: 1、新A强化患者归拢与管理，每月1场相关会议覆盖； 2、B转A，客户每月一场病例主题会议，讨论或分享； 3、覆盖陈G,赵XN,每季度1-2场升级治晕治痛观念。 | AU6: 每月1-2场省立牵头三方会议资源支持
A7: 苏州大学附属第二医院 | B7: TOP | C7: 何方禹 | D7: 卢星翰 | E7: 正式准入 | F7: 是 | G7: 18w/月 | H7: 仅神经内科&耳鼻喉科有权限处方 | I7: 432 | J7: 536 | K7: 444 | L7: 500 | M7: 564 | O7: 500+ | Q7: 5 | R7: 4 | S7: 1 | T7: 7 | U7: 13 | V7: 25 | W7: 8 | X7: 4 | Y7: 3 | Z7: 1 | AA7: 0 | AB7: =IFERROR(SUMIFS('top&core医院客户DDD'!$R$4:$R$557,'top&core医院客户DDD'!$A$4:$A$557,$A7,'top&core医院客户DDD'!$F$4:$F$557,LEFT(AB$2,1))/SUMIFS('top&core医院客户DDD'!$R$4:$R$557,'top&core医院客户DDD'!$A$4:$A$557,$A7),"") -> 0.81560284 | AC7: =IFERROR(SUMIFS('top&core医院客户DDD'!$R$4:$R$557,'top&core医院客户DDD'!$A$4:$A$557,$A7,'top&core医院客户DDD'!$F$4:$F$557,LEFT(AC$2,1))/SUMIFS('top&core医院客户DDD'!$R$4:$R$557,'top&core医院客户DDD'!$A$4:$A$557,$A7),"") -> 0.056737589 | AD7: =IFERROR(SUMIFS('top&core医院客户DDD'!$R$4:$R$557,'top&core医院客户DDD'!$A$4:$A$557,$A7,'top&core医院客户DDD'!$F$4:$F$557,LEFT(AD$2,1))/SUMIFS('top&core医院客户DDD'!$R$4:$R$557,'top&core医院客户DDD'!$A$4:$A$557,$A7),"") -> 0.12765957 | AE7: =IFERROR(SUMIFS('top&core医院客户DDD'!$R$4:$R$557,'top&core医院客户DDD'!$A$4:$A$557,$A7,'top&core医院客户DDD'!$F$4:$F$557,LEFT(AE$2,1))/SUMIFS('top&core医院客户DDD'!$R$4:$R$557,'top&core医院客户DDD'!$A$4:$A$557,$A7),"") -> 0 | AF7: 4 | AG7: 1 | AH7: 2 | AI7: 0 | AJ7: 1 | AK7: 0 | AL7: 1000+ | AM7: 1000 | AN7: 700 | AO7: 100 | AP7: 150 | AQ7: 50 | AR7: 院内单次处方限制及药占比影响 C类客户面较少 A类客户专家门诊虹吸效应不足且存在竞品在院内 | AS7: 院外药店引流减少药占比影响 拓展C类客户面 A类客户持续深挖，提高处方率 | AT7: 院外引流延长DOT减少限量影响 协助完成偏头痛VM相关研究 PSR每月定期复盘，共识目标，解决需求 大型学术会议覆盖，提高科室头痛头晕知名度 | AU7: 医学部协助研究 外部大型会议授课/主持提高头痛头晕知名度 PO、三方覆盖 省级学会活动参与任职
A8: 青岛市市立医院 | B8: CORE | C8: 张鑫 | D8: 李明晖 | E8: 未准入 | F8: 不适用 | I8: 472 | J8: 492 | K8: 456 | L8: 460 | M8: 484 | O8: 300+ | Q8: 3 | R8: 6 | S8: 0.5 | T8: 6 | U8: 20 | V8: 15 | W8: 8 | X8: 3 | Y8: 1 | Z8: 4 | AA8: 0 | AB8: =IFERROR(SUMIFS('top&core医院客户DDD'!$R$4:$R$557,'top&core医院客户DDD'!$A$4:$A$557,$A8,'top&core医院客户DDD'!$F$4:$F$557,LEFT(AB$2,1))/SUMIFS('top&core医院客户DDD'!$R$4:$R$557,'top&core医院客户DDD'!$A$4:$A$557,$A8),"") -> 0.62809917 | AC8: =IFERROR(SUMIFS('top&core医院客户DDD'!$R$4:$R$557,'top&core医院客户DDD'!$A$4:$A$557,$A8,'top&core医院客户DDD'!$F$4:$F$557,LEFT(AC$2,1))/SUMIFS('top&core医院客户DDD'!$R$4:$R$557,'top&core医院客户DDD'!$A$4:$A$557,$A8),"") -> 0 | AD8: =IFERROR(SUMIFS('top&core医院客户DDD'!$R$4:$R$557,'top&core医院客户DDD'!$A$4:$A$557,$A8,'top&core医院客户DDD'!$F$4:$F$557,LEFT(AD$2,1))/SUMIFS('top&core医院客户DDD'!$R$4:$R$557,'top&core医院客户DDD'!$A$4:$A$557,$A8),"") -> 0.37190083 | AE8: =IFERROR(SUMIFS('top&core医院客户DDD'!$R$4:$R$557,'top&core医院客户DDD'!$A$4:$A$557,$A8,'top&core医院客户DDD'!$F$4:$F$557,LEFT(AE$2,1))/SUMIFS('top&core医院客户DDD'!$R$4:$R$557,'top&core医院客户DDD'!$A$4:$A$557,$A8),"") -> 0 | AF8: 4 | AG8: 0 | AH8: 3 | AI8: 1 | AJ8: 0 | AK8: 0 | AL8: 500+ | AM8: 500 | AN8: 200 | AO8: 115 | AP8: 185 | AQ8: 0 | AR8: 1.专诊打造不足，增加头痛/眩晕专诊量，归拢患者 2.提升足量足疗程观念，拓展患者画像 3.加强患者管理 4.组建MDT专家团队 | AS8: 1.融动神内和耳鼻喉客户增加专诊量2.明确患者画像，提供病例正反馈 3.组建MDT专家团队，加强会议交流 | AT8: 1、增加专诊，提升患者归拢与管理 2、C类客户明确患者画像，提高推荐率 3、A/C类客户会议覆盖 | AU8: 三方会主席/讲者/讨论
A9: 南京脑科医院 | B9: CORE | C9: 郑家成 | D9: 徐燕 | E9: 单患临采 | F9: 不适用 | G9: 不适用 | H9: 不适用 | I9: 392 | J9: 236 | K9: 192 | L9: 260 | M9: 460 | O9: 300+ | Q9: 4.25 | R9: 5 | S9: 7 | T9: 3 | U9: 24 | V9: 20 | W9: 13 | X9: 4 | Y9: 6 | Z9: 2 | AA9: 1 | AB9: =IFERROR(SUMIFS('top&core医院客户DDD'!$R$4:$R$557,'top&core医院客户DDD'!$A$4:$A$557,$A9,'top&core医院客户DDD'!$F$4:$F$557,LEFT(AB$2,1))/SUMIFS('top&core医院客户DDD'!$R$4:$R$557,'top&core医院客户DDD'!$A$4:$A$557,$A9),"") -> 0.72173913 | AC9: =IFERROR(SUMIFS('top&core医院客户DDD'!$R$4:$R$557,'top&core医院客户DDD'!$A$4:$A$557,$A9,'top&core医院客户DDD'!$F$4:$F$557,LEFT(AC$2,1))/SUMIFS('top&core医院客户DDD'!$R$4:$R$557,'top&core医院客户DDD'!$A$4:$A$557,$A9),"") -> 0.034782609 | AD9: =IFERROR(SUMIFS('top&core医院客户DDD'!$R$4:$R$557,'top&core医院客户DDD'!$A$4:$A$557,$A9,'top&core医院客户DDD'!$F$4:$F$557,LEFT(AD$2,1))/SUMIFS('top&core医院客户DDD'!$R$4:$R$557,'top&core医院客户DDD'!$A$4:$A$557,$A9),"") -> 0 | AE9: =IFERROR(SUMIFS('top&core医院客户DDD'!$R$4:$R$557,'top&core医院客户DDD'!$A$4:$A$557,$A9,'top&core医院客户DDD'!$F$4:$F$557,LEFT(AE$2,1))/SUMIFS('top&core医院客户DDD'!$R$4:$R$557,'top&core医院客户DDD'!$A$4:$A$557,$A9),"") -> 0.24347826 | AF9: 8 | AG9: 3 | AH9: 1 | AI9: 1 | AJ9: 0 | AK9: 0 | AL9: 500+ | AM9: 500 | AN9: 400 | AO9: 25 | AP9: 50 | AQ9: 25 | AR9: 1、头痛客户观念还有大幅升级空间，增加患者画像 2、头晕客户观念薄弱，且参加会议意愿度较低，科室开展会议难度大 3、B类客户多，且分散度很大 4、精神科客户诊断差，观念薄弱 | AS9: 1、增加患者画像 2、筛选客户 3、提高客户诊断及观念 | AT9: 1、对于头痛客户分患者画像传递，逐一突破，增加患者画像使用 数 2、对于眩晕客户，撬动其参会意愿度 3、B类客户，广覆盖，筛选高质量客户培养 4、精神科客户多开展GD会，观念传递 | AU9: 1、线上会议（对于线下参会意愿度低的客户先洗刷观念） 2、每周定期po会 3、大客户定期协防，赋能
A10: 南通大学附属医院 | B10: CORE | C10: 何方禹 | D10: 周丽丽 | E10: 未准入 | F10: 不适用 | G10: 不适用 | H10: 不适用 | I10: 316 | J10: 312 | K10: 356 | L10: 404 | M10: 420 | O10: 300+ | Q10: 4 | R10: 3 | S10: 0 | T10: 5 | U10: 15 | V10: 20 | W10: 6 | X10: 2 | Y10: 2 | Z10: 2 | AA10: 0 | AB10: =IFERROR(SUMIFS('top&core医院客户DDD'!$R$4:$R$557,'top&core医院客户DDD'!$A$4:$A$557,$A10,'top&core医院客户DDD'!$F$4:$F$557,LEFT(AB$2,1))/SUMIFS('top&core医院客户DDD'!$R$4:$R$557,'top&core医院客户DDD'!$A$4:$A$557,$A10),"") -> 0.31428571 | AC10: =IFERROR(SUMIFS('top&core医院客户DDD'!$R$4:$R$557,'top&core医院客户DDD'!$A$4:$A$557,$A10,'top&core医院客户DDD'!$F$4:$F$557,LEFT(AC$2,1))/SUMIFS('top&core医院客户DDD'!$R$4:$R$557,'top&core医院客户DDD'!$A$4:$A$557,$A10),"") -> 0.085714286 | AD10: =IFERROR(SUMIFS('top&core医院客户DDD'!$R$4:$R$557,'top&core医院客户DDD'!$A$4:$A$557,$A10,'top&core医院客户DDD'!$F$4:$F$557,LEFT(AD$2,1))/SUMIFS('top&core医院客户DDD'!$R$4:$R$557,'top&core医院客户DDD'!$A$4:$A$557,$A10),"") -> 0.6 | AE10: =IFERROR(SUMIFS('top&core医院客户DDD'!$R$4:$R$557,'top&core医院客户DDD'!$A$4:$A$557,$A10,'top&core医院客户DDD'!$F$4:$F$557,LEFT(AE$2,1))/SUMIFS('top&core医院客户DDD'!$R$4:$R$557,'top&core医院客户DDD'!$A$4:$A$557,$A10),"") -> 0 | AF10: 1 | AG10: 3 | AH10: 1 | AI10: 1 | AJ10: 0 | AK10: 0 | AL10: 1000+ | AM10: 1000 | AN10: 230 | AO10: 182 | AP10: 528 | AQ10: 60 | AR10: 南通大学附属医院为CORE医院，是东二区300+梯队的标杆核心院。tth由3月316稳定爬升至7月420，呈持续上行，月均已在300+梯队；9月TTH目标880、Q4月均目标800+，仍有翻倍增量空间。门诊结构：头痛门诊4个/周、头痛客户3人；眩晕门诊暂为0但眩晕客户5人（耳鼻喉眩晕方向）有基础。标签客户15人、活跃客户仅6人，沉睡池大。客户与观念呈「底重金字塔」：阶梯治疗1人、止痛优选3人、短期治痛1人、治痛管理仅1人（张鲁平），资深治痛管理/治痛管理大师均为0；A客户2人（蔡可夫、李爱红，贡献31.4%）、B客户2人（贡献8.6%）、C客户2人（张鲁平等，贡献60%）、D客户0。贡献高度集中——张鲁平(耳鼻喉眩晕C类)一人贡献近六成，9月目标300、7月已220，是绝对主力，但其观念已到治痛管理，需上推资深治痛管理；多数B类脑血管(柯开富、曹茂红、樊兴娟、倪耀辉、成亚琴、张元媛、张云峰、顾晓苏、赵映红)及D类其它科室(疼痛/其它)仍为「不管不治」，7月tth基本为0，是医院级最大未开发池。最大瓶颈：准入标签「未准入」，卡在处方最后一公里。 | AS10: 1) 头部巩固扩量：张鲁平(治痛管理→资深治痛管理)维持并借前庭性偏头痛专病/号源扩容做标杆；蔡可夫、李爱红(A类头痛)上推治痛管理； 2) 中部观念上移：把止痛优选/短期治痛群体（柯开富、曹茂红、尤小东等）往治痛管理/短期治痛推，积累病例； 3) 底部批量破冰：9名B类脑血管「不管不治」客户（樊兴娟、倪耀辉、成亚琴、张元媛、张云峰、顾晓苏、赵映红等）通过一场脑血管科室会+逐人破冰批量唤醒进阶梯治疗； 4) 渠道借力：依托头痛专诊(蔡可夫4/周、李爱红8/周、陈鑫4/周)做治痛管理路径示范；眩晕方向(张鲁平、尤小东、胡松群、殷勇、刘浩)攻前庭性偏头痛血管风险患者； 5) 准入破冰：推动「未准入」转准入打通处方；补244标签、推动头痛/眩晕专诊与号源扩容做大患者池。 | AT10: 头部客户(张鲁平、蔡可夫、李爱红)每月≥2次高频拜访巩固并扩量，借前庭性偏头痛/头痛共病专诊扩容做大患者池并做转介网络；中部客户(柯开富、曹茂红、尤小东)依托专诊与科室会做观念上移、积累治痛管理病例；9名「不管不治」脑血管客户通过一场脑血管科室会+会后逐人破冰批量唤醒，并补全244标签(张元媛、张云峰、顾晓苏、缪秀华、李晓飞、郑冬冬等仍缺标签)；眩晕方向借区域眩晕会认前庭性偏头痛患者、优先瑞美吉泮用于血管风险者；D类(蒋锐、秦毅彬疼痛、李晓飞、郑冬冬)从其它科室培育，先以头痛/眩晕相关适应症切入；推动「未准入」转准入、开设/扩容头痛与眩晕专诊号源；对潜力但量未起的客户持续每月1-2次破冰拜访。 | AU10: 医学部循证（偏头痛-抑郁焦虑共病、前庭性偏头痛、血管风险、CGRP机制）资料与讲者支持；脑血管科室会+9人破冰带教支持；区域头痛/眩晕沙龙及COE会议名额；「未准入」转准入的医学/市场协同与院方准入协调；244标签系统录入与专诊/号源院方协调；张鲁平等头部客户的资深治痛管理上推与转介网络带教。
A11: 南通市第一人民医院 | B11: CORE | C11: 何方禹 | D11: 周丽丽 | E11: 未准入 | F11: 不适用 | G11: 不适用 | H11: 不适用 | I11: 280 | J11: 396 | K11: 336 | L11: 332 | M11: 392 | O11: 300+ | Q11: 2 | R11: 2 | S11: 1 | T11: 3 | U11: 9 | V11: 20 | W11: 5 | X11: 1 | Y11: 2 | Z11: 2 | AA11: 0 | AB11: =IFERROR(SUMIFS('top&core医院客户DDD'!$R$4:$R$557,'top&core医院客户DDD'!$A$4:$A$557,$A11,'top&core医院客户DDD'!$F$4:$F$557,LEFT(AB$2,1))/SUMIFS('top&core医院客户DDD'!$R$4:$R$557,'top&core医院客户DDD'!$A$4:$A$557,$A11),"") -> 0.020408163 | AC11: =IFERROR(SUMIFS('top&core医院客户DDD'!$R$4:$R$557,'top&core医院客户DDD'!$A$4:$A$557,$A11,'top&core医院客户DDD'!$F$4:$F$557,LEFT(AC$2,1))/SUMIFS('top&core医院客户DDD'!$R$4:$R$557,'top&core医院客户DDD'!$A$4:$A$557,$A11),"") -> 0.030612245 | AD11: =IFERROR(SUMIFS('top&core医院客户DDD'!$R$4:$R$557,'top&core医院客户DDD'!$A$4:$A$557,$A11,'top&core医院客户DDD'!$F$4:$F$557,LEFT(AD$2,1))/SUMIFS('top&core医院客户DDD'!$R$4:$R$557,'top&core医院客户DDD'!$A$4:$A$557,$A11),"") -> 0.94897959 | AE11: =IFERROR(SUMIFS('top&core医院客户DDD'!$R$4:$R$557,'top&core医院客户DDD'!$A$4:$A$557,$A11,'top&core医院客户DDD'!$F$4:$F$557,LEFT(AE$2,1))/SUMIFS('top&core医院客户DDD'!$R$4:$R$557,'top&core医院客户DDD'!$A$4:$A$557,$A11),"") -> 0 | AF11: 4 | AG11: 0 | AH11: 0 | AI11: 0 | AJ11: 1 | AK11: 0 | AL11: 1000+ | AM11: 700 | AN11: 105 | AO11: 175 | AP11: 385 | AQ11: 35 | AR11: 1.7月TTH 392，处于"300+"梯队，环比增长18.1%，连续2个月攀升，增长势能强劲，距500+梯队仅一步之遥； 2.客户结构严重失衡：C类客户董政协1人贡献7月销量的94%（368/392），头部依赖风险极高；A类2人（朱向阳、杨家伟）合计仅贡献8，与分型定位严重不匹配；B类7人合计12，人均处方量极低；D类空白； 3.13位目标客户中仅5人7月有处方（活跃率38%），8人处于零处方状态，其中6人为"不管不治"观念层级，破冰开发任务艰巨； 4.专诊资源未充分转化：朱向阳、杨家伟均开设头痛专诊（4次/月），但处方转化极低；董政协头晕/眩晕专诊运营良好，可作为标杆复制； 5.观念层级分布：阶梯治疗4人、止痛优选0人、短期治痛0人、治痛管理0人、资深治痛管理1人、治痛管理大师0人，中高层观念客户稀缺，观念提升空间大。 | AS11: 策略一【头部维稳+标杆打造】：以董政协主任为核心，推动其从"资深治痛管理"向"治痛管理大师"进阶，打造前庭性偏头痛全程管理标杆，通过科室病例讨论、区域学术会议发挥辐射带动效应，确保核心贡献持续增长； 策略二【A类激活+专诊转化】：重点激活朱向阳、杨家伟两位头痛专诊A类客户，加速观念从"不管不治/阶梯治疗"提升至"止痛优选/治痛管理"，推动专诊号源扩容与244标签建设，将专诊患者流量转化为处方量； 策略三【B类分层运营】：7位B类客户按状态分层——成长型（李燕、陈蓝）上量、断方型（朱连海）激活、零起步型（曹志勇、陆珍辉、郭啸鸣、邵良、汪晗）破冰，以"脑血管病合并偏头痛共病管理"为统一切入点，提升整体活跃率与人均处方量； 策略四【耳鼻喉VM开发】：秦阳、吴昊两位耳鼻喉科头晕/眩晕客户，以前庭性偏头痛识别与鉴别诊断为切入点，推动眩晕专诊建设，拓展VM患者治疗覆盖。 | AT11: 1.9月协助董政协主任开展1次"前庭性偏头痛全程管理"科室病例讨论会，覆盖神内+耳鼻喉全体13位目标客户，目标带动≥3位B/C类客户观念提升； 2.9月每周1次朱向阳头痛专诊前拜访，递送急性期+预防治疗指南，目标9月处方量从8提升至30，新增预防治疗患者2例； 3.9月优先安排杨家伟深度回访，分析断方原因并制定激活方案，目标9月重新实现首方并稳定至≥4例患者； 4.9月对7位B类客户实施分层拜访：成长型每两周1次聚焦上量、断方型优先1次深度回访+每两周1次激活、零起步型每两周1次破冰，目标9月B类活跃客户从2人增至5人； 5.9月协同秦阳、吴昊推动耳鼻喉科眩晕专诊建设，以前庭性偏头痛鉴别诊断为学术抓手，目标9月秦阳稳定处方≥4例、吴昊实现首方≥2例； 6.9月推动全院244标签完善（目前仅3人有标签），目标新增标签客户≥4人，提升院内系统偏头痛/眩晕患者识别与归拢率； 7.9月目标：全院TTH从392提升至500（+27.6%），活跃客户从5人增至9人，A类客户贡献占比从2%提升至15%。 | AU11: 1.学术资料：偏头痛急性期及预防性治疗最新指南/共识、前庭性偏头痛ICHD-3诊断标准及鉴别诊断流程图、脑血管病合并偏头痛共病管理文献、瑞美吉泮循证医学资料包（含2小时无痛率、长期安全性、MMD改善、心血管安全性数据）； 2.会议支持：9月科室"前庭性偏头痛全程管理"病例讨论会（讲者课件、会议场地、参会激励），目标覆盖13位客户；区域学术会议/城市会讲者平台与参会名额； 3.物料支持：头痛/眩晕专诊患者随访登记表、MMD记录卡、患者教育手册、门诊头痛快速筛查表（含心血管风险评估模块）、瑞美吉泮临床数据速查卡； 4.院方协调：专诊号源扩容审批支持、244标签及出诊简介标签系统录入支持； 5.人力资源：MICS/DM/RPM协同拜访资源（重点支持破冰客户与断方激活）、上级医院头痛/眩晕中心专家会诊/转诊对接、新人破冰拜访带教支持。
A12: 苏州市立医院 | B12: CORE | C12: 何方禹 | D12: 杜研 | E12: 常备临采 | F12: 不适用 | G12: 不适用 | H12: 不适用 | I12: 264 | J12: 344 | K12: 308 | L12: 308 | M12: 392 | O12: 300+ | Q12: 6 | R12: 4 | S12: 0 | T12: 3 | U12: 23 | V12: 20 | W12: 10 | X12: 5 | Y12: 4 | Z12: 1 | AA12: 0 | AB12: =IFERROR(SUMIFS('top&core医院客户DDD'!$R$4:$R$557,'top&core医院客户DDD'!$A$4:$A$557,$A12,'top&core医院客户DDD'!$F$4:$F$557,LEFT(AB$2,1))/SUMIFS('top&core医院客户DDD'!$R$4:$R$557,'top&core医院客户DDD'!$A$4:$A$557,$A12),"") -> 0.42857143 | AC12: =IFERROR(SUMIFS('top&core医院客户DDD'!$R$4:$R$557,'top&core医院客户DDD'!$A$4:$A$557,$A12,'top&core医院客户DDD'!$F$4:$F$557,LEFT(AC$2,1))/SUMIFS('top&core医院客户DDD'!$R$4:$R$557,'top&core医院客户DDD'!$A$4:$A$557,$A12),"") -> 0.41836735 | AD12: =IFERROR(SUMIFS('top&core医院客户DDD'!$R$4:$R$557,'top&core医院客户DDD'!$A$4:$A$557,$A12,'top&core医院客户DDD'!$F$4:$F$557,LEFT(AD$2,1))/SUMIFS('top&core医院客户DDD'!$R$4:$R$557,'top&core医院客户DDD'!$A$4:$A$557,$A12),"") -> 0.12244898 | AE12: =IFERROR(SUMIFS('top&core医院客户DDD'!$R$4:$R$557,'top&core医院客户DDD'!$A$4:$A$557,$A12,'top&core医院客户DDD'!$F$4:$F$557,LEFT(AE$2,1))/SUMIFS('top&core医院客户DDD'!$R$4:$R$557,'top&core医院客户DDD'!$A$4:$A$557,$A12),"") -> 0.030612245 | AF12: 6 | AG12: 2 | AH12: 1 | AI12: 1 | AJ12: 0 | AK12: 0 | AL12: 1000+ | AM12: 1000 | AN12: 350 | AO12: 300 | AP12: 100 | AQ12: 250 | AR12: ①活跃客户数不足：23位目标客户8月活跃仅10人(活跃率43%)，距目标20差10人；13人零处方(9位脑血管B类全零+沈明强断方+刘迎梅/沈蓉/吴冠会零)，空白巨大。 ②止痛优选+观念客户少：止痛优选仅1人(邓邦鱼)、短期治痛2、治痛管理1，'观念客户'(止痛优选及以上)合计仅4/23；57%(13人)处'不管不治'底层，观念金字塔'底重'，是销量增长核心瓶颈。 ③VM客户尤其耳鼻喉客户面少、深度不够：科室神内21+ENT1+其它1，耳鼻喉仅邓邦鱼1人；眩晕门诊0/周、VM(占眩晕15-20%)诊疗处方基本空白；邓邦鱼量36→20跌、刘迎梅断方、朱伟低量，VM'有方向无体系'。 | AS12: 1.头部A类稳量上移：付建忠(专诊8/月→资深/大师+预防渗透+GD会讲者/代言)、冯红选(专诊4→8扩容稳住+升代言)、王媚瑕(巩固起量+专诊扩容+升倡导)、沈明强(优先激活断方恢复+补244)。2.活跃客户扩容：9位沉睡脑血管B类(周华/王锋/邱晨红/邓晓雷/江玲玲/孙沁怡/丁园/黄开梅/朱浩)按'补244→STEP1打标签→差异化挂号杠杆→开专病门诊/增号源'批量破冰；高门诊零处方吴冠会(24/月)、沈蓉(8/月)优先PSR随访+打标签激活；王薇(16/月)补244撬动；目标Q4活跃10→20。3.观念金字塔上移+止痛优选扩容(补②)：Freezer→Tryer(13→≤3)、Tryer→Repeater止痛优选(1→≥3)、Advocator(2→≥6)、Ambassador(1→≥3)；以GD会+指南+病例统一抬升。4.VM/耳鼻喉专项突破(补③)：邓邦鱼设眩晕专诊+VM筛查稳量上移；朱伟VM筛查+跨科(神内→ENT)转诊；刘迎梅重启痛晕专诊模块+打标签激活；清单扩容新增1-2位ENT眩晕/VM KOL(见客户名单末行)，建VM筛查流程(ICHD-3)，严守Do/Don't(仅急性期、75mg按需、不超适应症、GCMA审批)。5.KOL金字塔与244扩容(补④)：244标签9→≥18/23(14位缺失优先补全)；代言(Ambassador)由2→3人(赵中/付建忠/冯红选)；倡导(Advocator)由2→≥6人(付建忠/冯红选/王媚瑕/邓朋/冯倩/邓邦鱼)；讲者TTT+GD会+区域会放大peer影响。 | AT12: 1.9月协助付建忠维持头痛专诊8/月满负荷，冯红选/王媚瑕专诊4→8扩容，赵中申请'头痛/情绪共病'专病门诊并增号源，门诊地图/互联网医院完成专诊标注。2.每次专诊/出诊前递送偏头痛预防治疗指南，月发作≥2次患者按指南评估预防需求，头部持续新增全程管理患者。3.9月以GD会开展1次科室'偏头痛全程管理'病例讨论会，付建忠/王媚瑕主讲，覆盖神内+耳鼻喉目标客户，会后1周未到场一对一补访。4.邓邦鱼推动设眩晕专诊+建VM筛查流程(ICHD-3)，朱伟/刘迎梅完善VM标签+跨科转诊，严守VM推广Do/Don't。5.9位沉睡脑血管B类(周华等)分批补全244标签+出诊简介标签(STEP1打标签)，按'科室会批量/一对一先行/区域会预热/开专病门诊/增模块号源'差异化杠杆破冰，推动不管不治→阶梯。6.吴冠会(24/月)优先PSR电话/微信随访既往患者重建信心并补244标签，王薇/沈蓉/沈明强补244标签撬动高门诊量；每次拜访带1典型病例强化规范治疗。7.清单扩容：摸排耳鼻喉眩晕/头痛亚专业新增1-2位目标医生(客户名单末行示意)，纳入244标签与VM专项管理。 | AU12: 1.偏头痛预防治疗最新指南/共识、前庭性偏头痛ICHD-3诊断标准、抑郁焦虑-偏头痛共病文献、瑞美吉泮循证包(2小时无痛率/安全性)。2.9月科室'偏头痛全程管理'GD会名额、GCMA审批幻灯片、讲者TTT赋能(付建忠/王媚瑕/冯红选)。3.门诊地图/互联网医院专诊标注资源、专病门诊/加号审批协调。4.244标签系统录入支持、出诊简介标签优化工具(STEP1)、VM筛查表/VM质控共识/眩晕专诊建设工具包(话术单页、VM宣教单页、随访工具、眩晕日记模板)。5.PSR对既往处方患者电话/微信随访模板+疗效反馈收集、零新处方医生入门培训包、首方信心建立工具、同伴经验分享。6.上级医院头痛中心会诊/转诊资源、区域头痛学科建设平台学术活动名额、ENT眩晕/VM专项学术资源。
A13: 安徽医科大学第一附属医院 | B13: TOP | C13: 卜先峰 | D13: 杨胜运/许恺丽 | E13: 正式准入 | F13: 否 | G13: 无 | H13: 无限制 | I13: 328 | J13: 300 | K13: 280 | L13: 340 | M13: 364 | O13: 300+ | Q13: 2.25 | R13: 4 | S13: 0 | T13: 5 | U13: 15 | V13: 20 | W13: 10 | X13: 3 | Y13: 6 | Z13: 1 | AA13: 0 | AB13: =IFERROR(SUMIFS('top&core医院客户DDD'!$R$4:$R$557,'top&core医院客户DDD'!$A$4:$A$557,$A13,'top&core医院客户DDD'!$F$4:$F$557,LEFT(AB$2,1))/SUMIFS('top&core医院客户DDD'!$R$4:$R$557,'top&core医院客户DDD'!$A$4:$A$557,$A13),"") -> 0.36263736 | AC13: =IFERROR(SUMIFS('top&core医院客户DDD'!$R$4:$R$557,'top&core医院客户DDD'!$A$4:$A$557,$A13,'top&core医院客户DDD'!$F$4:$F$557,LEFT(AC$2,1))/SUMIFS('top&core医院客户DDD'!$R$4:$R$557,'top&core医院客户DDD'!$A$4:$A$557,$A13),"") -> 0.2967033 | AD13: =IFERROR(SUMIFS('top&core医院客户DDD'!$R$4:$R$557,'top&core医院客户DDD'!$A$4:$A$557,$A13,'top&core医院客户DDD'!$F$4:$F$557,LEFT(AD$2,1))/SUMIFS('top&core医院客户DDD'!$R$4:$R$557,'top&core医院客户DDD'!$A$4:$A$557,$A13),"") -> 0.34065934 | AE13: =IFERROR(SUMIFS('top&core医院客户DDD'!$R$4:$R$557,'top&core医院客户DDD'!$A$4:$A$557,$A13,'top&core医院客户DDD'!$F$4:$F$557,LEFT(AE$2,1))/SUMIFS('top&core医院客户DDD'!$R$4:$R$557,'top&core医院客户DDD'!$A$4:$A$557,$A13),"") -> 0 | AF13: 7 | AG13: 0 | AH13: 3 | AI13: 0 | AJ13: 0 | AK13: 0 | AL13: 500+ | AM13: 480 | AN13: 312 | AO13: 96 | AP13: 48 | AQ13: 24 | AR13: 升级AB客户观念，扩大cd客户面 | AS13: AB客户强客情，学术观念升级，cd客户科室会议覆盖，学术观念共识 | AT13: A客户通过系列会议打造专家圈层B客户强客情，以张龙主任牵头，打造专家圈 CD客户 拓展耳鼻喉科 疼痛科，开展科室会议，拓展客户面 | AU13: 1：安徽头痛小组系列会议2：脑血管主题系列会议
A14: 青岛市西海岸医院 | B14: CORE | C14: 张鑫 | D14: 陈彩虹 | E14: 未准入 | F14: 不适用 | G14: 不适用 | H14: 不适用 | I14: 308 | J14: 308 | K14: 332 | L14: 336 | M14: 320 | O14: 300+ | Q14: 1 | R14: 2 | S14: 1 | T14: 3 | U14: 9 | V14: 9 | W14: 6 | X14: 2 | Y14: 1 | Z14: 1 | AA14: 2 | AB14: =IFERROR(SUMIFS('top&core医院客户DDD'!$R$4:$R$557,'top&core医院客户DDD'!$A$4:$A$557,$A14,'top&core医院客户DDD'!$F$4:$F$557,LEFT(AB$2,1))/SUMIFS('top&core医院客户DDD'!$R$4:$R$557,'top&core医院客户DDD'!$A$4:$A$557,$A14),"") -> 0.63291139 | AC14: =IFERROR(SUMIFS('top&core医院客户DDD'!$R$4:$R$557,'top&core医院客户DDD'!$A$4:$A$557,$A14,'top&core医院客户DDD'!$F$4:$F$557,LEFT(AC$2,1))/SUMIFS('top&core医院客户DDD'!$R$4:$R$557,'top&core医院客户DDD'!$A$4:$A$557,$A14),"") -> 0 | AD14: =IFERROR(SUMIFS('top&core医院客户DDD'!$R$4:$R$557,'top&core医院客户DDD'!$A$4:$A$557,$A14,'top&core医院客户DDD'!$F$4:$F$557,LEFT(AD$2,1))/SUMIFS('top&core医院客户DDD'!$R$4:$R$557,'top&core医院客户DDD'!$A$4:$A$557,$A14),"") -> 0.30379747 | AE14: =IFERROR(SUMIFS('top&core医院客户DDD'!$R$4:$R$557,'top&core医院客户DDD'!$A$4:$A$557,$A14,'top&core医院客户DDD'!$F$4:$F$557,LEFT(AE$2,1))/SUMIFS('top&core医院客户DDD'!$R$4:$R$557,'top&core医院客户DDD'!$A$4:$A$557,$A14),"") -> 0.063291139 | AF14: 4 | AG14: 0 | AH14: 1 | AI14: 1 | AJ14: 0 | AK14: 0 | AL14: 500+ | AM14: 500 | AN14: 250 | AO14: 100 | AP14: 50 | AQ14: 100 | AR14: 1、医院为头痛中心大三甲医院，产品当前状态为未准入，院内渠道暂未开放 2、头痛、眩晕专诊已开设，每周头痛门诊1次、眩晕门诊1次，A/B/C/D类客户均有布局 3、神经内科、疼痛科、耳鼻喉科均覆盖为目标客户，部分医生已开展专诊，但还有大量医生处于“不管不治”低观念阶段 4、历史TTH月销量维持300+水平，A类核心客户张亮贡献主要销量，其余客户潜力未释放且处方不连续 | AS14: 1、优先推进产品院内准入做青医本部的工作，打通院内渠道2、深耕已有专诊的A/C类客户，巩固核心产出3、激活B/D类客户，推动低观念医生完成观念升级4、借力头痛/眩晕专诊门诊，落地规范化诊疗路径，挖掘增量患者5、分层管理客户，实现A客户稳住基本盘、B/C/D客户观念升阶 | AT14: 1、准入方面：对接本部同事跟进院内采购、药剂科，梳理准入流程，准备完整产品资料，每周四为拜访日，借助跨部门同事力量协助进院 2、核心A客户张亮维护：跟进头痛专诊运行，门诊宣传以及PSR患者管理，跨平台交流资深治痛管理理念 3、C类客户李宏：依托眩晕专诊，推动观念从短期治痛升级至治痛管理，挖掘VM患者增量；4、潜力客户激活：贾春燕、孟超等，传递阶梯治疗、止痛优选理念，尝试门诊患者教育；针对滕继军、杨丽英等未破冰客户，从病例和GD会议切入，破除不管不治现状 5、专诊赋能：头痛、眩晕专诊门诊，提供诊疗工具资料，协助识别标签患者；耳鼻喉杨博文、黄天桥拓展头晕头痛患者机会 6、月度跟踪TTH销量，对比9月目标，复盘各客户观念转化与处方变化 | AU14: 准入方面需要跨部门和领导协防
A15: 苏州市中医医院 | B15: CORE | C15: 何方禹 | D15: 卢星翰 | E15: 未准入 | F15: 不适用 | G15: 不适用 | H15: 不适用 | I15: 336 | J15: 300 | K15: 224 | L15: 168 | M15: 284 | O15: 低于300 | Q15: 1 | R15: 1 | S15: 0 | T15: 3 | U15: 7 | V15: 9 | W15: 2 | X15: 1 | Y15: 1 | Z15: 0 | AA15: 0 | AB15: =IFERROR(SUMIFS('top&core医院客户DDD'!$R$4:$R$557,'top&core医院客户DDD'!$A$4:$A$557,$A15,'top&core医院客户DDD'!$F$4:$F$557,LEFT(AB$2,1))/SUMIFS('top&core医院客户DDD'!$R$4:$R$557,'top&core医院客户DDD'!$A$4:$A$557,$A15),"") -> 0.92957746 | AC15: =IFERROR(SUMIFS('top&core医院客户DDD'!$R$4:$R$557,'top&core医院客户DDD'!$A$4:$A$557,$A15,'top&core医院客户DDD'!$F$4:$F$557,LEFT(AC$2,1))/SUMIFS('top&core医院客户DDD'!$R$4:$R$557,'top&core医院客户DDD'!$A$4:$A$557,$A15),"") -> 0 | AD15: =IFERROR(SUMIFS('top&core医院客户DDD'!$R$4:$R$557,'top&core医院客户DDD'!$A$4:$A$557,$A15,'top&core医院客户DDD'!$F$4:$F$557,LEFT(AD$2,1))/SUMIFS('top&core医院客户DDD'!$R$4:$R$557,'top&core医院客户DDD'!$A$4:$A$557,$A15),"") -> 0.070422535 | AE15: =IFERROR(SUMIFS('top&core医院客户DDD'!$R$4:$R$557,'top&core医院客户DDD'!$A$4:$A$557,$A15,'top&core医院客户DDD'!$F$4:$F$557,LEFT(AE$2,1))/SUMIFS('top&core医院客户DDD'!$R$4:$R$557,'top&core医院客户DDD'!$A$4:$A$557,$A15),"") -> 0 | AF15: 1 | AG15: 0 | AH15: 0 | AI15: 1 | AJ15: 0 | AK15: 0 | AL15: 1000+ | AM15: 600 | AN15: 420 | AO15: 60 | AP15: 120 | AQ15: 0 | AR15: 诊断率较低，B\C采用阶梯疗法 科内对于头痛头晕不是特别重视 | AS15: 定期覆盖科主任，提高其头痛眩晕观念得到科主任支持，助力A\C发展 协助相关研究，提高科室知名度 | AT15: 通过协助入组研究延长DOT 刘凯鸣、张甦琳影响PPPD和VM时间界限，提高共病诊断率 | AU15: 江苏省眩晕学会任职 医学部协助完成VM研究 全国眩晕平台授课提高知名度
A16: 南京市第一医院 | B16: CORE | C16: 郑家成 | D16: 孙娟 | E16: 直联药店 | F16: 不适用 | G16: 不适用 | H16: 不适用 | I16: 184 | J16: 200 | K16: 220 | L16: 216 | M16: 280 | O16: 低于300 | Q16: 1 | R16: 1 | S16: 2 | T16: 3 | U16: 7 | V16: 13 | W16: 4 | X16: 1 | Y16: 1 | Z16: 2 | AA16: 0 | AB16: =IFERROR(SUMIFS('top&core医院客户DDD'!$R$4:$R$557,'top&core医院客户DDD'!$A$4:$A$557,$A16,'top&core医院客户DDD'!$F$4:$F$557,LEFT(AB$2,1))/SUMIFS('top&core医院客户DDD'!$R$4:$R$557,'top&core医院客户DDD'!$A$4:$A$557,$A16),"") -> 0.11428571 | AC16: =IFERROR(SUMIFS('top&core医院客户DDD'!$R$4:$R$557,'top&core医院客户DDD'!$A$4:$A$557,$A16,'top&core医院客户DDD'!$F$4:$F$557,LEFT(AC$2,1))/SUMIFS('top&core医院客户DDD'!$R$4:$R$557,'top&core医院客户DDD'!$A$4:$A$557,$A16),"") -> 0.057142857 | AD16: =IFERROR(SUMIFS('top&core医院客户DDD'!$R$4:$R$557,'top&core医院客户DDD'!$A$4:$A$557,$A16,'top&core医院客户DDD'!$F$4:$F$557,LEFT(AD$2,1))/SUMIFS('top&core医院客户DDD'!$R$4:$R$557,'top&core医院客户DDD'!$A$4:$A$557,$A16),"") -> 0.82857143 | AE16: =IFERROR(SUMIFS('top&core医院客户DDD'!$R$4:$R$557,'top&core医院客户DDD'!$A$4:$A$557,$A16,'top&core医院客户DDD'!$F$4:$F$557,LEFT(AE$2,1))/SUMIFS('top&core医院客户DDD'!$R$4:$R$557,'top&core医院客户DDD'!$A$4:$A$557,$A16),"") -> 0 | AF16: 1 | AG16: 2 | AH16: 0 | AI16: 1 | AJ16: 0 | AK16: 0 | AL16: 500+ | AM16: 350 | AN16: 50 | AO16: 40 | AP16: 250 | AQ16: 10 | AR16: A客户只有一个头痛专病门诊且观念在阶梯治疗阶段；B客户门诊患者类型比较杂无法聚拢患者；C专病门诊客户无处方经验导致不敢推荐，有经验的C客户无专病门诊导致患者类型不聚集，效率低 | AS16: A客户迭代观念增加推荐，B客户收集正反馈提高认可度，C客户增加专病门诊 | AT16: 增加对A类的客情拜访并提供专业的指南等资料，并增加邀请参加会议的机会，内外结合一起迭代观念，后期也要增加专病门诊和相关人员，形成团队；B类客户更加关注门诊中偏头痛患者的回访，增加正反馈，及时复诊，增加医生的认可度和知名度；C类有经验的客户要增加专病门诊，聚拢患者，并和无经验的专病门诊客户联动，一带一输出正向观念，一起进步成长 | AU16: 老板随访、日常客情、学会任职、高质量三方会
A17: 昆山市第一人民医院 | B17: CORE | C17: 何方禹 | D17: 黄义杰 | E17: 未准入 | F17: 不适用 | G17: 不适用 | H17: 不适用 | I17: 128 | J17: 178 | K17: 208 | L17: 264 | M17: 280 | O17: 低于300 | Q17: 1 | R17: 0 | S17: 1 | T17: 4 | U17: 5 | V17: 14 | W17: 5 | X17: 3 | Y17: 2 | Z17: 0 | AA17: 0 | AB17: =IFERROR(SUMIFS('top&core医院客户DDD'!$R$4:$R$557,'top&core医院客户DDD'!$A$4:$A$557,$A17,'top&core医院客户DDD'!$F$4:$F$557,LEFT(AB$2,1))/SUMIFS('top&core医院客户DDD'!$R$4:$R$557,'top&core医院客户DDD'!$A$4:$A$557,$A17),"") -> 0.66666667 | AC17: =IFERROR(SUMIFS('top&core医院客户DDD'!$R$4:$R$557,'top&core医院客户DDD'!$A$4:$A$557,$A17,'top&core医院客户DDD'!$F$4:$F$557,LEFT(AC$2,1))/SUMIFS('top&core医院客户DDD'!$R$4:$R$557,'top&core医院客户DDD'!$A$4:$A$557,$A17),"") -> 0.33333333 | AD17: =IFERROR(SUMIFS('top&core医院客户DDD'!$R$4:$R$557,'top&core医院客户DDD'!$A$4:$A$557,$A17,'top&core医院客户DDD'!$F$4:$F$557,LEFT(AD$2,1))/SUMIFS('top&core医院客户DDD'!$R$4:$R$557,'top&core医院客户DDD'!$A$4:$A$557,$A17),"") -> 0 | AE17: =IFERROR(SUMIFS('top&core医院客户DDD'!$R$4:$R$557,'top&core医院客户DDD'!$A$4:$A$557,$A17,'top&core医院客户DDD'!$F$4:$F$557,LEFT(AE$2,1))/SUMIFS('top&core医院客户DDD'!$R$4:$R$557,'top&core医院客户DDD'!$A$4:$A$557,$A17),"") -> 0 | AF17: 2 | AG17: 2 | AH17: 0 | AI17: 1 | AJ17: 0 | AK17: 0 | AL17: 800+ | AM17: 600 | AN17: 240 | AO17: 180 | AP17: 120 | AQ17: 60 | AR17: 1.7月TTH 280，处于"低于300"梯队，距离300梯队仅一步之遥，增长势能强劲。 2.A类仅1人（张炎）贡献占57%，头部依赖严重；B类9人，人均处方量低；C类4人完全空白； 3.14位目标客户中仅4人7月有处方（活跃率29%），6人零处方+4人断方，空白市场巨大； 4.仅1人达治痛管理，5人停留在不管不治，3人阶梯治疗，观念提升是销量增长的核心杠杆； 5.专头痛专诊1个+眩晕专诊2个，专诊患者中偏头痛/前庭性偏头痛识别率和处方率低； 6.跨耳鼻喉科4位医生全部零处方，前庭性偏头痛（占眩晕患者15-20%）诊疗完全空白，是重要增量方向； 7.吴亚平（抑郁焦虑亚专业）门诊中偏头痛共病率高达30-50%，目前完全未识别和处方。 | AS17: 1：以张炎头痛专诊为核心，推动专诊号源扩容（4→6次/月）+预防性治疗渗透，打造科室学术标杆，发挥辐射带动作用； 2：9位B类客户按状态分层运营——成长型（任洁明）上量、刚首方型（马召玺、杨华）稳量、断方型（钱小燕、张蕾）激活、零起步型（陆丽芸、缪桂华、王一鸣）首方、跨亚专业型（吴亚平）共病切入，目标9月B类活跃客户从2人提升至7人； 3：以前庭性偏头痛为统一切入点，4位耳鼻喉科医生分两组推进——有专诊组（丁小军、谷李欣）建立筛查流程+跨科转诊，无专诊组（邓建华、任亮）联动拜访+鉴别诊断能力提升，目标9月实现耳鼻喉科零的突破； 4：以张炎主任为讲者，9月开展1次科室"偏头痛全程管理"病例讨论会，覆盖神内+耳鼻喉全体目标客户，推动整体观念层级上移，目标治痛管理及以上客户从1人增至3人。 | AT17: 1.9月协助张炎主任提交头痛专诊加号申请，目标专诊从4次/月增至8次/月； 2.每次专诊前递送偏头痛预防性治疗指南/文献，目标9月新增预防治疗患者5例； 3.联合科室开展1次"偏头痛全程管理"病例讨论会，张炎主讲，覆盖神内+耳鼻喉全体目标客户； 4.协助建立头痛专诊患者随访登记表，对月发作≥2次患者主动随访评估预防治疗需求。 1.任洁明：重点沟通脑血管病合并偏头痛共病管理，建立门诊头痛筛查流程，目标9月80片； 2.马召玺/杨华：每两周拜访1次，携带典型病例，强化急性期规范治疗观念，目标各32片； 3.钱小燕/张蕾：首次拜访了解断方原因，随访既往处方患者收集疗效反馈，重建处方信心，目标各20-24片； 4.陆丽芸/缪桂华/王一鸣：从急性治疗便捷性切入，降低首方门槛，每两周拜访携带病例，目标各12-20片； 5.吴亚平：以共病管理为话题切入，提供偏头痛与焦虑抑郁共病资料，目标首方32片。 6.丁小军/谷李欣：以前庭性偏头痛为切入点，提供ICHD-3诊断标准，协助建立专诊筛查流程，推动与神内头痛专诊转诊协作，目标各32片； 7.邓建华/任亮：联动拜访营造科室处方氛围，以前庭性偏头痛鉴别诊断为切入点，先从1-2例典型患者入手建立信心，目标各12片。 8.9月中旬开展1次科室病例讨论会，张炎主任主讲"偏头痛全程管理"，邀请神内+耳鼻喉全体14位目标客户参加； 9.会后1周内对未到场客户进行一对一补访，递送会议资料及核心观点； 10.每次拜访携带1个典型病例，持续强化规范治疗观念，推动客户观念层级逐阶上移。 | AU17: 1.偏头痛急性期最新指南/共识、前庭性偏头痛ICHD-3诊断标准、抑郁焦虑与偏头痛共病管理文献、瑞美吉泮循证医学资料包（含2小时无痛率、安全性）； 2.会9月科室"偏头痛全程管理"病例讨论会，目标覆盖14位客户； 3.门诊头痛患者快速筛查表、前庭性偏头痛鉴别诊断工具、患者随访登记表、患者教育手册、瑞美吉泮核心卖点速查卡、典型病例集（每周更新）； 4.上级医院头痛中心专家会诊/转诊资源，协助推动神经内科头痛专诊与耳鼻喉科眩晕专诊的跨科转诊协作机制； 5.协助协调门诊办公室头痛专诊加号审批流程（张炎4→6次/月）； 6.PSR对既往处方患者电话/微信随访模板及支持，疗效反馈收集与整理； 7.零新处方医生入门培训资料包、首方信心建立工具、同伴经验分享（同科室处方医生病例交流）； 8.精神心理科/神经科抑郁焦虑亚专业医生使用瑞美吉泮的病例经验分享，共病患者筛查量表。
A18: 青岛市中医医院 | B18: CORE | C18: 张鑫 | D18: 冯雅琪 | E18: 未准入 | F18: 不适用 | G18: 不适用 | H18: 不适用 | I18: 248 | J18: 304 | K18: 356 | L18: 328 | M18: 256 | O18: 低于300 | Q18: 3 | R18: 1 | S18: 2 | T18: 7 | U18: 13 | V18: 15 | W18: 12 | X18: 1 | Y18: 5 | Z18: 5 | AA18: 1 | AB18: =IFERROR(SUMIFS('top&core医院客户DDD'!$R$4:$R$557,'top&core医院客户DDD'!$A$4:$A$557,$A18,'top&core医院客户DDD'!$F$4:$F$557,LEFT(AB$2,1))/SUMIFS('top&core医院客户DDD'!$R$4:$R$557,'top&core医院客户DDD'!$A$4:$A$557,$A18),"") -> 0.40983607 | AC18: =IFERROR(SUMIFS('top&core医院客户DDD'!$R$4:$R$557,'top&core医院客户DDD'!$A$4:$A$557,$A18,'top&core医院客户DDD'!$F$4:$F$557,LEFT(AC$2,1))/SUMIFS('top&core医院客户DDD'!$R$4:$R$557,'top&core医院客户DDD'!$A$4:$A$557,$A18),"") -> 0.06557377 | AD18: =IFERROR(SUMIFS('top&core医院客户DDD'!$R$4:$R$557,'top&core医院客户DDD'!$A$4:$A$557,$A18,'top&core医院客户DDD'!$F$4:$F$557,LEFT(AD$2,1))/SUMIFS('top&core医院客户DDD'!$R$4:$R$557,'top&core医院客户DDD'!$A$4:$A$557,$A18),"") -> 0.52459016 | AE18: =IFERROR(SUMIFS('top&core医院客户DDD'!$R$4:$R$557,'top&core医院客户DDD'!$A$4:$A$557,$A18,'top&core医院客户DDD'!$F$4:$F$557,LEFT(AE$2,1))/SUMIFS('top&core医院客户DDD'!$R$4:$R$557,'top&core医院客户DDD'!$A$4:$A$557,$A18),"") -> 0 | AF18: 9 | AG18: 2 | AH18: 1 | AI18: 0 | AJ18: 0 | AK18: 0 | AL18: 300+ | AM18: 430 | AN18: 130 | AO18: 90 | AP18: 170 | AQ18: 40 | AR18: AC客户产出为主；B客户潜力需要释放； 目前仅有1位头痛客户，需要融动中青年客户转A； C客户处方客户多但稳定客户较少，需要培养大C客户 | AS18: 1.落地眩晕学会，借助学会搭建中医院MDT小圈子； 2.目前眩晕出诊客户（马晓维、陈卫）需要进阶观念，Q4会议资源覆盖，病例分享； 3.A客户于主任加强融动，借助PSR进行患者管理，推动进阶治痛管理大师 4.耳鼻喉科眩晕门诊与学会同步推动，同时加强病房管理，深挖耳鼻喉，培养稳定处方客户，及小C大C客户；（朱晓宁 葛洪洲 陈晓宇） | AT18: 1.晓宁主任学会筹备中，9月沟通院外宴请； 2.两位客户已上报DM，优先进行会议覆盖； 3.患者管理进行中，主任处于保守状态，通过会议影响； 4.对于耳鼻喉客户，继续系列会议的召开，进行病例积累，同步跟进朱主任进行门诊申请 | AU18: 眩晕学会需要RM DM、市场部进行协防； 学会后期承接，会议资源的覆盖
A19: 徐州矿务集团总医院暨徐州医科大学院第二附属医院 | B19: CORE | C19: 孟鈃 | D19: 章智程 | E19: 正式准入 | F19: 否 | G19: 无 | H19: 除急诊，其他门诊、病房全开放 | I19: 108 | J19: 72 | K19: 148 | L19: 180 | M19: 232 | O19: 低于300 | Q19: 6 | R19: 1 | S19: 7 | T19: 6 | U19: 11 | V19: 11 | W19: 6 | X19: 1 | Y19: 2 | Z19: 2 | AA19: 1 | AB19: =IFERROR(SUMIFS('top&core医院客户DDD'!$R$4:$R$557,'top&core医院客户DDD'!$A$4:$A$557,$A19,'top&core医院客户DDD'!$F$4:$F$557,LEFT(AB$2,1))/SUMIFS('top&core医院客户DDD'!$R$4:$R$557,'top&core医院客户DDD'!$A$4:$A$557,$A19),"") -> 0.017241379 | AC19: =IFERROR(SUMIFS('top&core医院客户DDD'!$R$4:$R$557,'top&core医院客户DDD'!$A$4:$A$557,$A19,'top&core医院客户DDD'!$F$4:$F$557,LEFT(AC$2,1))/SUMIFS('top&core医院客户DDD'!$R$4:$R$557,'top&core医院客户DDD'!$A$4:$A$557,$A19),"") -> 0.051724138 | AD19: =IFERROR(SUMIFS('top&core医院客户DDD'!$R$4:$R$557,'top&core医院客户DDD'!$A$4:$A$557,$A19,'top&core医院客户DDD'!$F$4:$F$557,LEFT(AD$2,1))/SUMIFS('top&core医院客户DDD'!$R$4:$R$557,'top&core医院客户DDD'!$A$4:$A$557,$A19),"") -> 0.4137931 | AE19: =IFERROR(SUMIFS('top&core医院客户DDD'!$R$4:$R$557,'top&core医院客户DDD'!$A$4:$A$557,$A19,'top&core医院客户DDD'!$F$4:$F$557,LEFT(AE$2,1))/SUMIFS('top&core医院客户DDD'!$R$4:$R$557,'top&core医院客户DDD'!$A$4:$A$557,$A19),"") -> 0.51724138 | AF19: 3 | AG19: 2 | AH19: 1 | AI19: 0 | AJ19: 0 | AK19: 0 | AL19: 800+ | AM19: 960 | AN19: 210 | AO19: 150 | AP19: 300 | AQ19: 300 | AR19: 1.门诊患者眩晕客户目前观念阶梯治疗，复诊率低2.病房使用瑞美吉泮的患者出院带药低，复诊率低 3.疼痛科因治疗费无法降瑞美吉泮加入到方案 | AS19: 1.和随访护士一起沟通，或者帮助随访，看看是否真实有随访，邀约复诊 2.对没有随访护士的病区，融动主任建立随访机制，或帮助随访 3.尝试引进小包装，与疼痛科融合治疗方案 | AU19: 1.会议赞助 2.荣院和肖需要三方会议
A20: 江苏省苏北人民医院 | B20: CORE | C20: 郑家成 | D20: 高佳怡 | E20: 未准入 | F20: 不适用 | G20: 不适用 | H20: 不适用 | I20: 180 | J20: 224 | K20: 252 | L20: 248 | M20: 212 | O20: 低于300 | Q20: 1 | R20: 2 | S20: 1 | T20: 3 | U20: 16 | V20: 8 | W20: 6 | X20: 1 | Y20: 4 | Z20: 1 | AA20: 0 | AB20: =IFERROR(SUMIFS('top&core医院客户DDD'!$R$4:$R$557,'top&core医院客户DDD'!$A$4:$A$557,$A20,'top&core医院客户DDD'!$F$4:$F$557,LEFT(AB$2,1))/SUMIFS('top&core医院客户DDD'!$R$4:$R$557,'top&core医院客户DDD'!$A$4:$A$557,$A20),"") -> 0.81132075 | AC20: =IFERROR(SUMIFS('top&core医院客户DDD'!$R$4:$R$557,'top&core医院客户DDD'!$A$4:$A$557,$A20,'top&core医院客户DDD'!$F$4:$F$557,LEFT(AC$2,1))/SUMIFS('top&core医院客户DDD'!$R$4:$R$557,'top&core医院客户DDD'!$A$4:$A$557,$A20),"") -> 0.18867925 | AD20: =IFERROR(SUMIFS('top&core医院客户DDD'!$R$4:$R$557,'top&core医院客户DDD'!$A$4:$A$557,$A20,'top&core医院客户DDD'!$F$4:$F$557,LEFT(AD$2,1))/SUMIFS('top&core医院客户DDD'!$R$4:$R$557,'top&core医院客户DDD'!$A$4:$A$557,$A20),"") -> 0 | AE20: =IFERROR(SUMIFS('top&core医院客户DDD'!$R$4:$R$557,'top&core医院客户DDD'!$A$4:$A$557,$A20,'top&core医院客户DDD'!$F$4:$F$557,LEFT(AE$2,1))/SUMIFS('top&core医院客户DDD'!$R$4:$R$557,'top&core医院客户DDD'!$A$4:$A$557,$A20),"") -> 0 | AF20: 4 | AG20: 1 | AH20: 1 | AI20: 0 | AJ20: 0 | AK20: 0 | AL20: 500+ | AM20: 500 | AN20: 200 | AO20: 150 | AP20: 100 | AQ20: 50 | AR20: 眩晕客户产出占比不够 | AS20: 耳鼻喉，神内眩晕重点跟进 | AT20: 市人医眩晕中心，苏北眩晕门诊 | AU20: 眩晕三方会，lb
A21: 青岛大学附属医院 | B21: CORE | C21: 张鑫 | D21: 冯雅琪 | E21: 未准入 | F21: 不适用 | G21: 不适用 | H21: 不适用 | I21: 152 | J21: 136 | K21: 136 | L21: 152 | M21: 188 | O21: 低于300 | Q21: 1 | R21: 1 | S21: 3 | T21: 6 | U21: 20 | V21: 20 | W21: 10 | X21: 1 | Y21: 7 | Z21: 1 | AA21: 1 | AB21: =IFERROR(SUMIFS('top&core医院客户DDD'!$R$4:$R$552,'top&core医院客户DDD'!$A$4:$A$552,$A21,'top&core医院客户DDD'!$F$4:$F$552,LEFT(AB$2,1))/SUMIFS('top&core医院客户DDD'!$R$4:$R$552,'top&core医院客户DDD'!$A$4:$A$552,$A21),"") -> 0.26315789 | AC21: =IFERROR(SUMIFS('top&core医院客户DDD'!$R$4:$R$552,'top&core医院客户DDD'!$A$4:$A$552,$A21,'top&core医院客户DDD'!$F$4:$F$552,LEFT(AC$2,1))/SUMIFS('top&core医院客户DDD'!$R$4:$R$552,'top&core医院客户DDD'!$A$4:$A$552,$A21),"") -> 0.47368421 | AD21: =IFERROR(SUMIFS('top&core医院客户DDD'!$R$4:$R$552,'top&core医院客户DDD'!$A$4:$A$552,$A21,'top&core医院客户DDD'!$F$4:$F$552,LEFT(AD$2,1))/SUMIFS('top&core医院客户DDD'!$R$4:$R$552,'top&core医院客户DDD'!$A$4:$A$552,$A21),"") -> 0.23684211 | AE21: =IFERROR(SUMIFS('top&core医院客户DDD'!$R$4:$R$552,'top&core医院客户DDD'!$A$4:$A$552,$A21,'top&core医院客户DDD'!$F$4:$F$552,LEFT(AE$2,1))/SUMIFS('top&core医院客户DDD'!$R$4:$R$552,'top&core医院客户DDD'!$A$4:$A$552,$A21),"") -> 0.026315789 | AF21: 7 | AG21: 3 | AH21: 0 | AI21: 0 | AJ21: 0 | AK21: 0 | AL21: 300+ | AM21: 400 | AN21: 70 | AO21: 180 | AP21: 110 | AQ21: 40 | AR21: 目前本部医院无头痛方向客户；客户处方面及深度急需拓展深挖； 增长较为缓慢 | AS21: 对于已破冰处方客户，会议覆盖加深治痛治晕观念； 筛选中青年客户，融动头痛眩晕方向发展；（王乃东/孙绍洋？） 小圈子宴请，目前已预约，加深客情，搭建青医MDT小圈子； 分客户拓展，共岗深挖客户潜力； | AT21: 1.破冰客户已梳理名单，报给DM，三方会议覆盖； 2.锁定王乃东/孙绍洋，做初步融动 3.对于小圈子宴请，已预约王乃东主任，暂定9月初； 4.共岗客户名单已梳理，沟通中 | AU21: DM及市场部、区域部共同协防孙妍萍主任及药剂科 推动青医临采
A22: 山东大学齐鲁医院 | B22: TOP | C22: 李路 | D22: TBA | E22: 未准入 | F22: 不适用 | G22: 不适用 | H22: 不适用 | I22: 203 | J22: 320 | K22: 288 | L22: 313 | M22: 178 | O22: 低于300 | Q22: 0 | R22: 2 | S22: 4 | T22: 2 | U22: 19 | V22: 16 | W22: 9 | X22: 2 | Y22: 7 | Z22: 0 | AA22: 0 | AB22: =IFERROR(SUMIFS('top&core医院客户DDD'!$R$4:$R$555,'top&core医院客户DDD'!$A$4:$A$555,$A22,'top&core医院客户DDD'!$F$4:$F$555,LEFT(AB$2,1))/SUMIFS('top&core医院客户DDD'!$R$4:$R$555,'top&core医院客户DDD'!$A$4:$A$555,$A22),"") -> 0.22988506 | AC22: =IFERROR(SUMIFS('top&core医院客户DDD'!$R$4:$R$555,'top&core医院客户DDD'!$A$4:$A$555,$A22,'top&core医院客户DDD'!$F$4:$F$555,LEFT(AC$2,1))/SUMIFS('top&core医院客户DDD'!$R$4:$R$555,'top&core医院客户DDD'!$A$4:$A$555,$A22),"") -> 0.77011494 | AD22: =IFERROR(SUMIFS('top&core医院客户DDD'!$R$4:$R$555,'top&core医院客户DDD'!$A$4:$A$555,$A22,'top&core医院客户DDD'!$F$4:$F$555,LEFT(AD$2,1))/SUMIFS('top&core医院客户DDD'!$R$4:$R$555,'top&core医院客户DDD'!$A$4:$A$555,$A22),"") -> 0 | AE22: =IFERROR(SUMIFS('top&core医院客户DDD'!$R$4:$R$555,'top&core医院客户DDD'!$A$4:$A$555,$A22,'top&core医院客户DDD'!$F$4:$F$555,LEFT(AE$2,1))/SUMIFS('top&core医院客户DDD'!$R$4:$R$555,'top&core医院客户DDD'!$A$4:$A$555,$A22),"") -> 0 | AF22: 8 | AG22: 1 | AH22: 0 | AI22: 0 | AJ22: 0 | AK22: 0 | AL22: 300+ | AM22: 320 | AN22: 64 | AO22: 192 | AP22: 48 | AQ22: 16 | AR22: 1、A客户对于六类优势人群未常规首选； 2、B对于单患者未达足剂量； 3、CD观念夯实不稳固。 | AS22: 1、学术会议影响观念，推动新的优势人群的认知； 2、强化患者后续风险，做好患者管理； 3、由AB影响改变CD的观念。 | AT22: 1、倡导六大优势人群常规首选，每月一场相关主题的会议； 2、相应群体确保足剂量足疗程，每月一场患教会传递，做好头痛日记的管理； 3、分享AB应用经验，每月围绕目标客户2场科室会。 | AU22: 每月1-2场三方会议覆盖含主席、讲者及讨论的名额
A23: 潍坊市人民医院 | B23: CORE | C23: 张鑫 | D23: 张鑫 | E23: 未准入 | F23: 不适用 | G23: 不适用 | H23: 不适用 | I23: 188 | J23: 196 | K23: 120 | L23: 140 | M23: 176 | O23: 低于300 | Q23: 0 | R23: 1 | S23: 4 | T23: 3 | U23: 10 | W23: 5 | X23: 1 | Y23: 1 | Z23: 3 | AA23: 0 | AB23: =IFERROR(SUMIFS('top&core医院客户DDD'!$R$4:$R$557,'top&core医院客户DDD'!$A$4:$A$557,$A23,'top&core医院客户DDD'!$F$4:$F$557,LEFT(AB$2,1))/SUMIFS('top&core医院客户DDD'!$R$4:$R$557,'top&core医院客户DDD'!$A$4:$A$557,$A23),"") -> 0.097560976 | AC23: =IFERROR(SUMIFS('top&core医院客户DDD'!$R$4:$R$557,'top&core医院客户DDD'!$A$4:$A$557,$A23,'top&core医院客户DDD'!$F$4:$F$557,LEFT(AC$2,1))/SUMIFS('top&core医院客户DDD'!$R$4:$R$557,'top&core医院客户DDD'!$A$4:$A$557,$A23),"") -> 0.68292683 | AD23: =IFERROR(SUMIFS('top&core医院客户DDD'!$R$4:$R$557,'top&core医院客户DDD'!$A$4:$A$557,$A23,'top&core医院客户DDD'!$F$4:$F$557,LEFT(AD$2,1))/SUMIFS('top&core医院客户DDD'!$R$4:$R$557,'top&core医院客户DDD'!$A$4:$A$557,$A23),"") -> 0.2195122 | AE23: =IFERROR(SUMIFS('top&core医院客户DDD'!$R$4:$R$557,'top&core医院客户DDD'!$A$4:$A$557,$A23,'top&core医院客户DDD'!$F$4:$F$557,LEFT(AE$2,1))/SUMIFS('top&core医院客户DDD'!$R$4:$R$557,'top&core医院客户DDD'!$A$4:$A$557,$A23),"") -> 0 | AF23: 2 | AG23: 2 | AH23: 1 | AI23: 0 | AJ23: 0 | AK23: 0 | AL23: 300+ | AM23: 308 | AN23: 0 | AO23: 184 | AP23: 112 | AQ23: 12 | AR23: 1、无核心专业的头痛医生，缺乏科室级学术标杆2、现有客户深度不够、缺少学术绑定，足量足疗程管理认知不深3、C类客户基数少、潜力未发觉 | AS23: 1、筛选科室意向高、学习意愿强的中青年医生，孵化为A类客户2、从单纯拜访 升级为学术绑定+诊疗观念统一。通过病例复盘、足量足疗程观念输出、打造核心B客户群 3、针对神内与耳鼻喉的眩晕中心进行广覆盖、扩充客户基数 | AT23: 1、梳理未定专业以及对头痛感兴趣的青年医师，锁定2-3位进行重点管理客户。优先邀请参加相关会议，、2、协助科室梳理诊疗流程、患者管理体系，打造科室特色亚专业3、4季度完成A客户打造、带动科室整体观念4、针对核心B客户，每周1次深度拜访。每次输出1个临床痛点、融动一个患者画像5、主动协助客户梳理门户患者病例，9月完成1-2例的典型病例，做好足量足疗程管路6、代言客户定制客户计划、提升客户认可度以及依赖度7、广覆盖C客户，开展常态化GD，低成本观念触达，筛选2-3位核心客户进行深度缔结，培养足量足疗程习惯 | AU23: 线上会一场，做耳鼻喉眩晕与神内眩晕的MDT，打通医院诊疗
A24: 淄博市中心医院 | B24: CORE | C24: 张鑫 | D24: 鲁景霄 | E24: 未准入 | F24: 不适用 | G24: 不适用 | H24: 不适用 | I24: 136 | J24: 124 | K24: 160 | L24: 152 | M24: 176 | O24: 低于300 | Q24: 2 | R24: 1 | S24: 8 | T24: 4 | U24: 14 | V24: 10 | W24: 7 | X24: 1 | Y24: 5 | Z24: 1 | AA24: 0 | AB24: =IFERROR(SUMIFS('top&core医院客户DDD'!$R$4:$R$557,'top&core医院客户DDD'!$A$4:$A$557,$A24,'top&core医院客户DDD'!$F$4:$F$557,LEFT(AB$2,1))/SUMIFS('top&core医院客户DDD'!$R$4:$R$557,'top&core医院客户DDD'!$A$4:$A$557,$A24),"") -> 0.27272727 | AC24: =IFERROR(SUMIFS('top&core医院客户DDD'!$R$4:$R$557,'top&core医院客户DDD'!$A$4:$A$557,$A24,'top&core医院客户DDD'!$F$4:$F$557,LEFT(AC$2,1))/SUMIFS('top&core医院客户DDD'!$R$4:$R$557,'top&core医院客户DDD'!$A$4:$A$557,$A24),"") -> 0.63636364 | AD24: =IFERROR(SUMIFS('top&core医院客户DDD'!$R$4:$R$557,'top&core医院客户DDD'!$A$4:$A$557,$A24,'top&core医院客户DDD'!$F$4:$F$557,LEFT(AD$2,1))/SUMIFS('top&core医院客户DDD'!$R$4:$R$557,'top&core医院客户DDD'!$A$4:$A$557,$A24),"") -> 0.090909091 | AE24: =IFERROR(SUMIFS('top&core医院客户DDD'!$R$4:$R$557,'top&core医院客户DDD'!$A$4:$A$557,$A24,'top&core医院客户DDD'!$F$4:$F$557,LEFT(AE$2,1))/SUMIFS('top&core医院客户DDD'!$R$4:$R$557,'top&core医院客户DDD'!$A$4:$A$557,$A24),"") -> 0 | AF24: 4 | AG24: 3 | AH24: 0 | AI24: 0 | AJ24: 0 | AK24: 0 | AL24: 300+ | AM24: 300 | AN24: 78 | AO24: 183 | AP24: 39 | AQ24: 0 | AR24: 偏头痛诊断率较低，阶梯治疗观念，瑞美推荐等级较低 | AS24: A客户头痛专病门诊深挖，B类客户提升偏头痛诊断率，提升瑞美推荐等级，C类客户提升VM诊断率，明确目标患者画像 | AT24: A客户头痛门诊CDSS提升病例规范化，深挖偏头痛患者潜力，覆盖PO及三方会议，B客户覆盖会议，提升偏头痛诊断率及瑞美推荐等级，C重点客户优先覆盖三方会议，外部观念影响，PSR协助随访患者，提升正反馈 | AU24: PO会议讲者。三方会议讲者或讨论
A25: 山东第二医科大学附属医院 | B25: CORE | C25: 青岛 | D25: TBA | E25: 未准入 | F25: 不适用 | G25: 不适用 | H25: 不适用 | I25: 100 | J25: 138 | K25: 76 | L25: 108 | M25: 80 | O25: 低于300 | Q25: 6 | R25: 3 | S25: 0 | T25: 0 | U25: 8 | W25: 5 | X25: 2 | Y25: 2 | Z25: 1 | AA25: 0 | AB25: =IFERROR(SUMIFS('top&core医院客户DDD'!$R$4:$R$557,'top&core医院客户DDD'!$A$4:$A$557,$A25,'top&core医院客户DDD'!$F$4:$F$557,LEFT(AB$2,1))/SUMIFS('top&core医院客户DDD'!$R$4:$R$557,'top&core医院客户DDD'!$A$4:$A$557,$A25),"") -> 0.8 | AC25: =IFERROR(SUMIFS('top&core医院客户DDD'!$R$4:$R$557,'top&core医院客户DDD'!$A$4:$A$557,$A25,'top&core医院客户DDD'!$F$4:$F$557,LEFT(AC$2,1))/SUMIFS('top&core医院客户DDD'!$R$4:$R$557,'top&core医院客户DDD'!$A$4:$A$557,$A25),"") -> 0.2 | AD25: =IFERROR(SUMIFS('top&core医院客户DDD'!$R$4:$R$557,'top&core医院客户DDD'!$A$4:$A$557,$A25,'top&core医院客户DDD'!$F$4:$F$557,LEFT(AD$2,1))/SUMIFS('top&core医院客户DDD'!$R$4:$R$557,'top&core医院客户DDD'!$A$4:$A$557,$A25),"") -> 0 | AE25: =IFERROR(SUMIFS('top&core医院客户DDD'!$R$4:$R$557,'top&core医院客户DDD'!$A$4:$A$557,$A25,'top&core医院客户DDD'!$F$4:$F$557,LEFT(AE$2,1))/SUMIFS('top&core医院客户DDD'!$R$4:$R$557,'top&core医院客户DDD'!$A$4:$A$557,$A25),"") -> 0 | AF25: 2 | AG25: 2 | AH25: 1 | AI25: 0 | AJ25: 0 | AK25: 0 | AL25: 300+ | AM25: 256 | AN25: 108 | AO25: 68 | AP25: 80 | AQ25: 0 | AR25: 1、头痛专诊患者归拢率低2、现有核心客户足量足疗程规范化观念薄弱3、眩晕科客户覆盖率低、潜力挖掘不足 | AS25: 1、协助科室沉淀头痛专病接诊体系，引导患者归拢，打造固定专病流量端口2、以病例随访+指南落地双抓手，纠正短期用药习惯，统一足量、足疗程、长周期管理理念 不单纯做产品拜访3、眩晕科客户全面盘点、覆盖、打造科室第二增长曲线 | AT25: 1、对接科室主任及核心骨干，沟通头痛亚专业规范化建设思路、开展科室小型宣教，明确典型偏头痛、复发性头痛患者的专病接诊路径，引导门诊分诊集中。2、对现有A/B核心客户执行一对一学术深耕拜访，每次拜访聚焦一个主题、核心客户全部建立足量足疗程、长周期管理的规范化诊疗习惯，患者复发率下降、持续用药率提升、3、对空白客户完成首轮学术触达，普及VM与各类眩晕的鉴别诊断、规范化用药基础认知，完成基础扫盲。4、筛选2–3名优质潜力客户，重点跟进、重点学术倾斜，通过病例分享、指南推送、门诊沟通，逐步培养眩晕处方习惯。
A26: 安徽省立医院 | B26: CORE | C26: 卜先峰 | D26: 洪剑 | E26: 未准入 | F26: 不适用 | G26: 不适用 | H26: 不适用 | I26: 188 | J26: 200 | K26: 84 | L26: 80 | M26: 164 | O26: 低于300 | Q26: 4 | R26: 2 | S26: 2 | T26: 7 | U26: 14 | V26: 5 | W26: 5 | X26: 2 | Y26: 2 | Z26: 1 | AA26: 0 | AB26: 0.47 | AC26: 0.21 | AD26: 0.32 | AE26: =IFERROR(SUMIFS('top&core医院客户DDD'!$R$4:$R$557,'top&core医院客户DDD'!$A$4:$A$557,$A26,'top&core医院客户DDD'!$F$4:$F$557,LEFT(AE$2,1))/SUMIFS('top&core医院客户DDD'!$R$4:$R$557,'top&core医院客户DDD'!$A$4:$A$557,$A26),"") -> 0 | AF26: 3 | AG26: 1 | AH26: 1 | AI26: 0 | AJ26: 0 | AK26: 0 | AL26: 300+ | AM26: 280 | AN26: 132 | AO26: 60 | AP26: 88 | AR26: 诊断观念落后不明确，推荐率低，院外药房到店率低 | AS26: 提高偏头痛的诊断率和推荐率，药房培训和协助，管理随访 | AT26: 围绕安徽省头痛小组建设发展，积极拓展科室头痛人员观念，眩晕中心建设安徽省的标杆，打造全省到全国的影响力 | AU26: 头痛专向会议覆盖，以安徽省眩晕中心建设开展VM的专向治疗标准和观念
A27: 徐州医科大学附属医院 | B27: Growth | C27: 孟鈃 | D27: 章智程 | E27: 处方外配 | F27: 不适用 | G27: 不适用 | H27: 不适用 | I27: 180 | J27: 200 | K27: 144 | L27: 128 | M27: 136 | O27: 低于300 | Q27: 2 | R27: 2 | S27: 15 | T27: 5 | U27: 11 | V27: 7 | W27: 5 | X27: 2 | Y27: 4 | Z27: 5 | AA27: 0 | AB27: =IFERROR(SUMIFS('top&core医院客户DDD'!$R$4:$R$554,'top&core医院客户DDD'!$A$4:$A$554,$A27,'top&core医院客户DDD'!$F$4:$F$554,LEFT(AB$2,1))/SUMIFS('top&core医院客户DDD'!$R$4:$R$554,'top&core医院客户DDD'!$A$4:$A$554,$A27),"") -> 0.73529412 | AC27: =IFERROR(SUMIFS('top&core医院客户DDD'!$R$4:$R$554,'top&core医院客户DDD'!$A$4:$A$554,$A27,'top&core医院客户DDD'!$F$4:$F$554,LEFT(AC$2,1))/SUMIFS('top&core医院客户DDD'!$R$4:$R$554,'top&core医院客户DDD'!$A$4:$A$554,$A27),"") -> 0.088235294 | AD27: =IFERROR(SUMIFS('top&core医院客户DDD'!$R$4:$R$554,'top&core医院客户DDD'!$A$4:$A$554,$A27,'top&core医院客户DDD'!$F$4:$F$554,LEFT(AD$2,1))/SUMIFS('top&core医院客户DDD'!$R$4:$R$554,'top&core医院客户DDD'!$A$4:$A$554,$A27),"") -> 0.17647059 | AE27: =IFERROR(SUMIFS('top&core医院客户DDD'!$R$4:$R$554,'top&core医院客户DDD'!$A$4:$A$554,$A27,'top&core医院客户DDD'!$F$4:$F$554,LEFT(AE$2,1))/SUMIFS('top&core医院客户DDD'!$R$4:$R$554,'top&core医院客户DDD'!$A$4:$A$554,$A27),"") -> 0 | AF27: 4 | AG27: 0 | AH27: 1 | AI27: 0 | AJ27: 0 | AK27: 0 | AL27: 500+ | AM27: 700 | AN27: 400 | AO27: 30 | AP27: 240 | AQ27: 30 | AR27: 1.头痛中心主任不重视头痛专病门诊没有稳定开展2.大量患者流到老专家观念比较差的客户手里 3.眩晕中心诊断不规范 | AS27: 1.融动头痛中心主任积极发展中心。2.其他可以申请头痛专病门诊的科室筛选愿意积极发展的中青年专家开展头痛专病门诊 3.眩晕中心诊断策略需要改变，从患者角度和治疗角度推荐使用瑞美吉泮 | AU27: LB、三方会
A28: 常州市第一人民医院 | B28: CORE | C28: 郑家成 | D28: 缪苏琴 | E28: 未准入 | F28: 不适用 | G28: 不适用 | H28: 不适用 | I28: 80 | J28: 128 | K28: 112 | L28: 120 | M28: 132 | O28: 低于300 | Q28: 2 | R28: 1 | S28: 2 | T28: 2 | U28: 4 | V28: 4 | W28: 2 | X28: 0 | Y28: 0 | Z28: 2 | AA28: 0 | AB28: =IFERROR(SUMIFS('top&core医院客户DDD'!$R$4:$R$557,'top&core医院客户DDD'!$A$4:$A$557,$A28,'top&core医院客户DDD'!$F$4:$F$557,LEFT(AB$2,1))/SUMIFS('top&core医院客户DDD'!$R$4:$R$557,'top&core医院客户DDD'!$A$4:$A$557,$A28),"") -> 0 | AC28: =IFERROR(SUMIFS('top&core医院客户DDD'!$R$4:$R$557,'top&core医院客户DDD'!$A$4:$A$557,$A28,'top&core医院客户DDD'!$F$4:$F$557,LEFT(AC$2,1))/SUMIFS('top&core医院客户DDD'!$R$4:$R$557,'top&core医院客户DDD'!$A$4:$A$557,$A28),"") -> 0 | AD28: =IFERROR(SUMIFS('top&core医院客户DDD'!$R$4:$R$557,'top&core医院客户DDD'!$A$4:$A$557,$A28,'top&core医院客户DDD'!$F$4:$F$557,LEFT(AD$2,1))/SUMIFS('top&core医院客户DDD'!$R$4:$R$557,'top&core医院客户DDD'!$A$4:$A$557,$A28),"") -> 1 | AE28: =IFERROR(SUMIFS('top&core医院客户DDD'!$R$4:$R$557,'top&core医院客户DDD'!$A$4:$A$557,$A28,'top&core医院客户DDD'!$F$4:$F$557,LEFT(AE$2,1))/SUMIFS('top&core医院客户DDD'!$R$4:$R$557,'top&core医院客户DDD'!$A$4:$A$557,$A28),"") -> 0 | AF28: 1 | AG28: 0 | AH28: 1 | AI28: 0 | AJ28: 0 | AK28: 0 | AL28: 300+ | AM28: 260 | AN28: 26 | AO28: 13 | AP28: 208 | AQ28: 13 | AR28: 1、头痛门诊医生经验不足，对头痛的诊断和识别能力较差 2、客户面太少需要拓展 | AS28: 1、A类客户要加大宣传，增加会议覆盖，并做好跟进； 2、B类客户迭代观念，从阶梯治疗到治痛管理 | AT28: 1、区域中青年PO会计划执行，做好会后跟进 2、客户数拓展后加强拜访频率 | AU28: 会议覆盖、学苑培训班
A29: 东南大学附属中大医院 | B29: CORE | C29: 郑家成 | D29: 孙娟 | E29: 直联药店 | F29: 不适用 | G29: 不适用 | H29: 不适用 | I29: 81 | J29: 110 | K29: 93 | L29: 115 | M29: 81 | O29: 低于300 | Q29: 2 | R29: 2 | S29: 2 | T29: 1 | U29: 8 | V29: 10 | W29: 5 | X29: 2 | Y29: 2 | Z29: 1 | AA29: 0 | AB29: =IFERROR(SUMIFS('top&core医院客户DDD'!$R$4:$R$557,'top&core医院客户DDD'!$A$4:$A$557,$A29,'top&core医院客户DDD'!$F$4:$F$557,LEFT(AB$2,1))/SUMIFS('top&core医院客户DDD'!$R$4:$R$557,'top&core医院客户DDD'!$A$4:$A$557,$A29),"") -> 0.80246914 | AC29: =IFERROR(SUMIFS('top&core医院客户DDD'!$R$4:$R$557,'top&core医院客户DDD'!$A$4:$A$557,$A29,'top&core医院客户DDD'!$F$4:$F$557,LEFT(AC$2,1))/SUMIFS('top&core医院客户DDD'!$R$4:$R$557,'top&core医院客户DDD'!$A$4:$A$557,$A29),"") -> 0.16049383 | AD29: =IFERROR(SUMIFS('top&core医院客户DDD'!$R$4:$R$557,'top&core医院客户DDD'!$A$4:$A$557,$A29,'top&core医院客户DDD'!$F$4:$F$557,LEFT(AD$2,1))/SUMIFS('top&core医院客户DDD'!$R$4:$R$557,'top&core医院客户DDD'!$A$4:$A$557,$A29),"") -> 0.037037037 | AE29: =IFERROR(SUMIFS('top&core医院客户DDD'!$R$4:$R$557,'top&core医院客户DDD'!$A$4:$A$557,$A29,'top&core医院客户DDD'!$F$4:$F$557,LEFT(AE$2,1))/SUMIFS('top&core医院客户DDD'!$R$4:$R$557,'top&core医院客户DDD'!$A$4:$A$557,$A29),"") -> 0 | AF29: 4 | AG29: 1 | AH29: 0 | AI29: 0 | AJ29: 0 | AK29: 0 | AL29: 300+ | AM29: 200 | AN29: 120 | AO29: 20 | AP29: 60 | AQ29: 0 | AR29: 每周2个头痛门诊，但是都有其他专业一起；耳鼻喉科客户观念较差 | AS29: A类客户要加大宣传，增加专诊次数，并做好回访；C类客户迭代观念，从阶梯治疗到治痛管理 | AT29: A类客户在门诊屏幕、分诊台做好分流，督促做好患者回访及时复诊，归拢患者收集正反馈；C类客户邀请参加内外部会议更新观念，改变处方习惯 | AU29: 三方会、GD/LB/PO、头痛头晕量表收集
A30: 山东省精神卫生中心 | B30: CORE | C30: 李路 | D30: 公茂伟 | E30: 未准入 | F30: 不适用 | G30: 不适用 | H30: 不适用 | I30: 168 | J30: 52 | K30: 68 | L30: 84 | M30: 72 | O30: 低于300 | Q30: 0 | R30: 0 | S30: 0 | T30: 0 | U30: 1 | V30: 6 | W30: 6 | X30: 1 | Y30: 0 | Z30: 0 | AA30: 5 | AB30: 0.05 | AC30: =IFERROR(SUMIFS('top&core医院客户DDD'!$R$4:$R$557,'top&core医院客户DDD'!$A$4:$A$557,$A30,'top&core医院客户DDD'!$F$4:$F$557,LEFT(AC$2,1))/SUMIFS('top&core医院客户DDD'!$R$4:$R$557,'top&core医院客户DDD'!$A$4:$A$557,$A30),"") -> 0 | AD30: =IFERROR(SUMIFS('top&core医院客户DDD'!$R$4:$R$557,'top&core医院客户DDD'!$A$4:$A$557,$A30,'top&core医院客户DDD'!$F$4:$F$557,LEFT(AD$2,1))/SUMIFS('top&core医院客户DDD'!$R$4:$R$557,'top&core医院客户DDD'!$A$4:$A$557,$A30),"") -> 0 | AE30: 0.95 | AF30: 1 | AG30: 2 | AH30: 0 | AI30: 0 | AJ30: 0 | AK30: 0 | AL30: 300+ | AM30: 363 | AN30: 23 | AO30: 0 | AP30: 0 | AQ30: 340 | AR30: 1成立头痛门诊 2增加MDT联合诊疗观念 3增加治痛观念进阶医生 | AS30: 1融动院长计划引进头痛专家计划 2成立融合门诊MDT诊断 3优秀病例分享圈 | AT30: 1以实现人才引进 2加速融合MDT圈子认识 3开始积累病例 | AU30: 每月2个名额参与三方会
A31: 青岛市精神卫生中心 | B31: CORE | C31: 张鑫 | D31: 李明晖 | E31: 批量临采 | F31: 不适用 | G31: 不适用 | H31: 不适用 | I31: 60 | J31: 80 | K31: 48 | L31: 48 | M31: 68 | O31: 低于300 | Q31: 3.25 | R31: 4 | S31: 0 | T31: 0 | U31: 0 | V31: 6 | W31: 2 | X31: 0 | Y31: 0 | Z31: 0 | AA31: 2 | AB31: =IFERROR(SUMIFS('top&core医院客户DDD'!$R$4:$R$557,'top&core医院客户DDD'!$A$4:$A$557,$A31,'top&core医院客户DDD'!$F$4:$F$557,LEFT(AB$2,1))/SUMIFS('top&core医院客户DDD'!$R$4:$R$557,'top&core医院客户DDD'!$A$4:$A$557,$A31),"") -> 0 | AC31: =IFERROR(SUMIFS('top&core医院客户DDD'!$R$4:$R$557,'top&core医院客户DDD'!$A$4:$A$557,$A31,'top&core医院客户DDD'!$F$4:$F$557,LEFT(AC$2,1))/SUMIFS('top&core医院客户DDD'!$R$4:$R$557,'top&core医院客户DDD'!$A$4:$A$557,$A31),"") -> 0 | AD31: =IFERROR(SUMIFS('top&core医院客户DDD'!$R$4:$R$557,'top&core医院客户DDD'!$A$4:$A$557,$A31,'top&core医院客户DDD'!$F$4:$F$557,LEFT(AD$2,1))/SUMIFS('top&core医院客户DDD'!$R$4:$R$557,'top&core医院客户DDD'!$A$4:$A$557,$A31),"") -> 0 | AE31: =IFERROR(SUMIFS('top&core医院客户DDD'!$R$4:$R$557,'top&core医院客户DDD'!$A$4:$A$557,$A31,'top&core医院客户DDD'!$F$4:$F$557,LEFT(AE$2,1))/SUMIFS('top&core医院客户DDD'!$R$4:$R$557,'top&core医院客户DDD'!$A$4:$A$557,$A31),"") -> 1 | AF31: 1 | AG31: 1 | AH31: 0 | AI31: 0 | AJ31: 0 | AK31: 0 | AL31: 300+ | AM31: 300 | AN31: 0 | AO31: 0 | AP31: 0 | AQ31: 300 | AR31: 1.D类客户既往无偏头痛诊断经验，偏头痛观念不足 2.无A类客户，头痛专诊数不足 | AS31: 1、通过GD会议，邀请参加三方会听课学习提升偏头痛诊断率； 2、积累正反馈病例，创造分享机会；与综合医院A类客户建立交流平台 3、增加专病门诊 | AT31: 1.利用GD会，三方会提升客户的偏头痛诊断观念2.组建MDT团队，提供病例正反馈提升用药信心 | AU31: 三方会议讲者/讨论
A32: 胜利油田中心医院 | B32: CORE | C32: 李路 | D32: TBA | E32: 常备临采 | F32: 不适用 | I32: 312 | J32: 416 | K32: 268 | L32: 104 | M32: 16 | O32: 低于300 | Q32: 1 | R32: 3 | S32: 1 | T32: 2 | U32: 15 | W32: 2 | X32: 1 | Y32: 1 | Z32: 0 | AA32: 0 | AB32: =IFERROR(SUMIFS(#REF!,#REF!,$A32,#REF!,LEFT(AB$2,1))/SUMIFS(#REF!,#REF!,$A32),"") | AC32: =IFERROR(SUMIFS(#REF!,#REF!,$A32,#REF!,LEFT(AC$2,1))/SUMIFS(#REF!,#REF!,$A32),"") | AD32: =IFERROR(SUMIFS(#REF!,#REF!,$A32,#REF!,LEFT(AD$2,1))/SUMIFS(#REF!,#REF!,$A32),"") | AE32: =IFERROR(SUMIFS(#REF!,#REF!,$A32,#REF!,LEFT(AE$2,1))/SUMIFS(#REF!,#REF!,$A32),"") | AF32: 2 | AG32: 0 | AH32: 0 | AI32: 0 | AJ32: 0 | AK32: 0

Sheet top&core医院客户DDD
X1: 注意合规表述
X2: 例如门诊增加，号源，标签，诊疗路径识别出机会，6大增长点
A3: 医院 | B3: 医院级别 | C3: 客户名 | D3: 科室 | E3: 亚专业 | F3: 客户分型 | G3: 是否list | H3: 244标签 | I3: 出诊简介中是否含有头痛/疼痛、头晕/眩晕等标签 | J3: 专诊标签 | K3: 专诊次数/月 | L3: 非专诊次数/月 | M3: 出诊次数/月 | N3: 3月tth预估实际 | O3: 4月tth预估实际 | P3: 5月tth预估实际 | Q3: 6月tth预估实际 | R3: 7月tth预估实际 | S3: 8月tth预估实际 | T3: 月销量变化 | U3: 现阶段观念评估（7月） | V3: 观念提升目标 | W3: 9月预估目标（2片装） | X3: 机会点 | Y3: 针对每一个机会点的行动计划 | Z3: 所需需求&支持
A4: 安徽省立医院 | B4: CORE | C4: 桂韦 | D4: 神经内科 | E4: 头痛 | F4: A | G4: 是 | H4: 是 | I4: 是 | J4: 头痛专诊 | K4: 12 | L4: 0 | M4: 12 | N4: 132 | O4: 116 | P4: 40 | Q4: 48 | R4: 120 | U4: 短期治痛（Advocator） | V4: 治痛管理（Ambassador） | W4: 120 | X4: 每周3个头痛专诊，患者归拢率高，省内患者口碑和号召力强 | Y4: 借助安徽省头痛小组建设，省内头痛专家个人影响力 | Z4: 围绕头痛建设的省内培训会和质控会议
A5: 安徽省立医院 | B5: CORE | C5: 程昭昭 | D5: 神经内科 | E5: 脑血管 | F5: B | G5: 是 | H5: 是 | I5: 否 | J5: 无专诊设置 | K5: 0 | L5: 16 | M5: 16 | N5: 24 | O5: 40 | P5: 16 | Q5: 20 | R5: 32 | U5: 止痛优选（Repeater） | V5: 短期治痛（Advocator） | W5: 40 | X5: 病区主任，头痛在科室的发展，患者依从性高 | Y5: 省内会议平台，提高自身的影响力和地位 | Z5: 线上线下PO会或者三方会的主席，省外会议交流
A6: 安徽省立医院 | B6: CORE | C6: 潘春晨 | D6: 耳鼻喉科 | E6: 头晕/眩晕 | F6: C | G6: 是 | H6: 是 | I6: 是 | J6: 无专诊设置 | K6: 0 | L6: 20 | M6: 20 | N6: 20 | O6: 32 | P6: 20 | Q6: 12 | R6: 4 | U6: 阶梯治疗（Tryer） | V6: 止痛优选（Repeater） | W6: 40 | X6: 每周开设2个眩晕专诊，发展晕痛方向，VM诊断率低 | Y6: 协助中青年医生职业和未来方向发展，安徽省内眩晕的领头人 | Z6: 眩晕中心建设支持和平台打造，个人在科室的影响力和发展
A7: 安徽省立医院 | B7: CORE | C7: 吴燕 | D7: 神经内科 | E7: 头晕/眩晕 | F7: C | G7: 是 | H7: 是 | I7: 是 | J7: 头晕/眩晕专诊 | K7: 4 | L7: 8 | M7: 12 | N7: 0 | O7: 0 | P7: 0 | Q7: 0 | R7: 4 | U7: 阶梯治疗（Tryer） | V7: 止痛优选（Repeater） | W7: 20 | X7: 开设神经内科的眩晕门诊，瑞美在眩晕治疗的认可，融动 | Z7: 客情融动，安徽省头痛小组发展
A8: 安徽省立医院 | B8: CORE | C8: 王梓 | D8: 神经内科 | E8: 头痛 | F8: A | G8: 是 | H8: 是 | I8: 是 | J8: 头痛专诊 | K8: 4 | L8: 0 | M8: 4 | N8: 8 | O8: 0 | P8: 0 | Q8: 0 | R8: 4 | U8: 阶梯治疗（Tryer） | V8: 止痛优选（Repeater） | W8: 12 | X8: 开设头痛专诊，跟随桂主任头痛方向研究，中青年的培养 | Y8: 作为医院青年头痛方向培养，用药和学术方向的提升，作为代言培育 | Z8: 青年的医生头痛交流会议
A9: 安徽省立医院 | B9: CORE | C9: 周裔翠 | D9: 耳鼻喉科 | E9: 头晕/眩晕 | F9: C | G9: 是 | H9: 是 | I9: 是 | J9: 无专诊设置 | K9: 0 | L9: 4 | M9: 4 | N9: 0 | O9: 0 | P9: 0 | Q9: 0 | R9: 0 | U9: 不管不治（Freezer） | V9: 止痛优选（Repeater） | W9: 12 | X9: 眩晕发展方向，VM的诊断和治疗欠缺 | Y9: 眩晕青年医生的交流和观念提升，收集病例 | Z9: 青年医生会议和病例分享
A10: 安徽省立医院 | B10: CORE | C10: 孙家强 | D10: 耳鼻喉科 | E10: 头晕/眩晕 | F10: C | G10: 是 | H10: 是 | I10: 是 | J10: 无专诊设置 | K10: 0 | L10: 16 | M10: 16 | N10: 0 | O10: 0 | P10: 0 | Q10: 0 | R10: 0 | U10: 不管不治（Freezer） | V10: 阶梯治疗（Tryer） | W10: 4 | X10: 科室主任，准入进院，科室号召和影响 | Y10: 省外大咖交流和个人影响力的提升 | Z10: 省外会议主席或者主持
A11: 安徽省立医院 | B11: CORE | C11: 吴元波 | D11: 神经内科 | E11: 脑血管 | F11: B | G11: 是 | H11: 是 | I11: 是 | J11: 无专诊设置 | K11: 0 | L11: 20 | M11: 20 | N11: 0 | O11: 12 | P11: 0 | Q11: 0 | R11: 0 | U11: 不管不治（Freezer） | V11: 阶梯治疗（Tryer） | W11: 4 | X11: 谨慎院外用药 | Y11: 高频拜访和产品传递 | Z11: 客情融动，安徽省头痛小组发展
A12: 安徽省立医院 | B12: CORE | C12: 吴蕾 | D12: 神经内科 | E12: 脑血管 | F12: B | G12: 是 | H12: 是 | I12: 是 | J12: 无专诊设置 | K12: 0 | L12: 16 | M12: 16 | N12: 0 | O12: 0 | P12: 0 | Q12: 0 | R12: 0 | U12: 不管不治（Freezer） | V12: 阶梯治疗（Tryer） | W12: 4 | X12: 对于青少年的用药感兴趣，院外用药顾虑 | Y12: 高频拜访，传递临床青少年的数据 | Z12: 会议讨论学习
A13: 安徽省立医院 | B13: CORE | C13: 宋笑凯 | D13: 神经内科 | E13: 癫痫 | F13: B | G13: 是 | H13: 否 | I13: 是 | J13: 无专诊设置 | K13: 0 | L13: 12 | M13: 12 | N13: 0 | O13: 0 | P13: 0 | Q13: 0 | R13: 0 | U13: 不管不治（Freezer） | V13: 阶梯治疗（Tryer） | W13: 4 | X13: 院外处方限制 | Y13: 高频拜访和产品传递 | Z13: 会议邀请讨论或听课学习
A14: 安徽省立医院 | B14: CORE | C14: 刘晓薇 | D14: 耳鼻喉科 | E14: 头晕/眩晕 | F14: C | G14: 是 | H14: 是 | I14: 是 | J14: 头晕/眩晕专诊 | K14: 4 | L14: 12 | M14: 16 | N14: 0 | O14: 0 | P14: 0 | Q14: 0 | R14: 0 | U14: 不管不治（Freezer） | V14: 阶梯治疗（Tryer） | W14: 4 | X14: 最早开展眩晕门诊，眩晕患者归拢高，顾虑院外用药 | Y14: 借助眩晕中心建设，改变主任观念和用药方案选择 | Z14: 围绕眩晕中心建设活动会议
A15: 安徽省立医院 | B15: CORE | C15: 侯晓燕 | D15: 耳鼻喉科 | E15: 头晕/眩晕 | F15: C | G15: 是 | H15: 否 | I15: 是 | J15: 无专诊设置 | K15: 0 | L15: 12 | M15: 12 | N15: 0 | O15: 0 | P15: 0 | Q15: 0 | R15: 0 | U15: 不管不治（Freezer） | V15: 阶梯治疗（Tryer） | W15: 4 | X15: 院外处方限制 | Y15: 高频拜访和产品传递 | Z15: 会议邀请讨论或听课学习
A16: 安徽省立医院 | B16: CORE | C16: 王俊 | D16: 耳鼻喉科 | E16: 头晕/眩晕 | F16: C | G16: 是 | H16: 否 | I16: 是 | J16: 无专诊设置 | K16: 0 | L16: 12 | M16: 12 | N16: 0 | O16: 0 | P16: 0 | Q16: 0 | R16: 0 | U16: 不管不治（Freezer） | V16: 阶梯治疗（Tryer） | W16: 4 | X16: 外科手术结合耳蜗偏头痛患者用药 | Y16: 高频拜访，沟通收集病例 | Z16: 病例分享
A17: 安徽省立医院 | B17: CORE | C17: 陈育华 | D17: 神经内科 | E17: 癫痫 | F17: B | G17: 是 | H17: 否 | I17: 是 | J17: 无专诊设置 | K17: 0 | L17: 12 | M17: 12 | N17: 0 | O17: 0 | P17: 0 | Q17: 0 | R17: 0 | U17: 不管不治（Freezer） | V17: 阶梯治疗（Tryer） | W17: 4 | X17: 顾虑院外用药，患者告知方案 | Y17: 高频拜访和产品传递 | Z17: 会议邀请讨论或听课学习
A18: 安徽省立医院 | B18: CORE | C18: 朱余友 | D18: 神经内科 | E18: 脑血管 | F18: B | G18: 是 | H18: 否 | I18: 是 | J18: 无专诊设置 | K18: 0 | L18: 12 | M18: 12 | N18: 0 | O18: 0 | P18: 0 | Q18: 0 | R18: 0 | U18: 不管不治（Freezer） | V18: 阶梯治疗（Tryer） | W18: 4 | X18: 脑血管共病患者，关注药物安全性 | Y18: 高频拜访和跟进尝试用药后，推荐会议参加 | Z18: 用药经验后会议主持
A19: 安徽医科大学第一附属医院 | B19: TOP | C19: 朱本藩 | D19: 疼痛科 | E19: 疼痛 | F19: D | G19: 是 | H19: 否 | I19: 是 | J19: 无专诊设置 | K19: 0 | L19: 2 | M19: 2 | N19: 0 | O19: 0 | P19: 0 | Q19: 20 | R19: 0 | U19: 不管不治（Freezer） | V19: 短期治痛（Advocator） | W19: 12 | X19: 已破冰，有足量足疗程观念，无患者管理 | Y19: LB会议融动，客情覆盖，融动协助患者随访，提高患者归拢 | Z19: lb会议资源
... A47: 安徽医科大学第一附属医院 | B47: TOP | C47: 蒋玉宝 | D47: 神经内科 | E47: 癫痫 | F47: B | G47: 否 | H47: 否 | I47: 否 | J47: 无专诊设置 | K47: 0 | L47: 2 | M47: 2 | N47: 4 | O47: 4 | P47: 0 | Q47: 0 | R47: 0 | U47: 不管不治（Freezer） | V47: 阶梯治疗（Tryer） | W47: 8 | X47: 王玉院长癫痫组员，有合并偏头痛患者人群 | Y47: 王玉院长牵头头痛小组融动，癫痫共病患者目标画像共识 | Z47: 王院长牵头头痛小组系列会议融动
A48: 常州市第一人民医院 | B48: CORE | C48: 薛海翔 | D48: 耳鼻喉科 | E48: 头晕/眩晕 | F48: C | G48: 是 | H48: 是 | I48: 是 | J48: 头晕/眩晕专诊 | K48: 4 | L48: 12 | M48: 16 | N48: 48 | O48: 88 | P48: 92 | Q48: 84 | R48: 112 | S48: 185 | U48: 短期治痛（Advocator） | V48: 资深治痛管理（Experienced Ambassador） | W48: 200 | X48: 诊疗路径识别出机会 | Y48: 搭建中青年学术交流平台；结合客户发展规划制定阶段性沟通计划 | Z48: 中青年专家平台；客户学术成长资源；患者管理项目支持；月度学术活动支持
A49: 常州市第一人民医院 | B49: CORE | C49: 李海峰 | D49: 耳鼻喉科 | E49: 头晕/眩晕 | F49: C | G49: 是 | H49: 是 | I49: 是 | J49: 头晕/眩晕专诊 | K49: 4 | L49: 4 | M49: 8 | N49: 8 | O49: 12 | P49: 12 | Q49: 8 | R49: 20 | S49: 44 | U49: 阶梯治疗（Tryer） | V49: 止痛优选（Repeater） | W49: 60 | X49: 号源增加 | Y49: 患者画像梳理；典型病例整理 | Z49: VM学术活动明确诊断和治疗策略
A50: 常州市第一人民医院 | B50: CORE | C50: 练学淦 | D50: 神经内科 | E50: 脑血管 | F50: B | G50: 是 | H50: 否 | I50: 是 | J50: 无专诊设置 | K50: 0 | L50: 8 | M50: 8 | N50: 4 | O50: 16 | P50: 8 | Q50: 0 | R50: 0 | S50: 0 | U50: 不管不治（Freezer） | V50: 不管不治（Freezer） | W50: 12 | X50: 诊疗路径识别出机会 | Y50: LB和其他专家交流经验，建立客户问题清单；匹配学术内容 | Z50: pim覆盖；脑血管病合并头痛跨领域会议
A51: 常州市第一人民医院 | B51: CORE | C51: 马晨晨 | D51: 神经内科 | E51: 头痛 | F51: A | G51: 是 | H51: 是 | I51: 是 | J51: 头痛专诊 | K51: 8 | L51: 0 | M51: 8 | N51: 0 | O51: 0 | P51: 0 | Q51: 0 | R51: 0 | S51: 0 | U51: 不管不治（Freezer） | V51: 不管不治（Freezer） | W51: 30 | X51: 诊疗路径识别出机会 | Y51: 增加拜访频率理，共识患者画像 | Z51: 脑血管病、头痛跨领域会议
A52: 常州市第一人民医院 | B52: CORE | C52: 丁俭 | D52: 神经内科 | E52: 脑血管 | F52: B | G52: 是 | H52: 否 | I52: 否 | J52: 无专诊设置 | K52: 0 | L52: 1 | M52: 1 | N52: 0 | O52: 4 | P52: 0 | Q52: 0 | R52: 0 | S52: 4 | U52: 不管不治（Freezer） | V52: 不管不治（Freezer） | W52: 12 | X52: 门诊增加 | Y52: pim、gd会议覆盖 | Z52: 脑血管病、头痛跨领域会议
A53: 常州市第一人民医院 | B53: CORE | C53: 岳春贤 | D53: 神经内科 | E53: 脑血管 | F53: B | G53: 是 | H53: 否 | I53: 否 | J53: 无专诊设置 | K53: 0 | L53: 1 | M53: 1 | N53: 0 | O53: 4 | P53: 0 | Q53: 0 | R53: 0 | S53: 4 | U53: 不管不治（Freezer） | V53: 不管不治（Freezer） | W53: 12 | X53: 门诊增加 | Y53: pim、gd会议覆盖 | Z53: 脑血管病、头痛跨领域会议
A54: 常州市第一人民医院 | B54: CORE | C54: 朱靓 | D54: 神经内科 | E54: 脑血管 | F54: B | G54: 是 | H54: 否 | I54: 否 | J54: 无专诊设置 | K54: 0 | L54: 1 | M54: 1 | N54: 12 | O54: 4 | P54: 0 | Q54: 28 | R54: 0 | S54: 0 | U54: 不管不治（Freezer） | V54: 不管不治（Freezer） | W54: 12 | X54: 诊疗路径识别出机会 | Y54: 增加拜访频率理，共识患者画像 | Z54: 脑血管病、头痛跨领域会议
A55: 东南大学附属中大医院 | B55: CORE | C55: 耿磊钰 | D55: 神经内科 | E55: 头痛 | F55: A | G55: 是 | H55: 是 | I55: 是 | J55: 头痛专诊 | K55: 4 | L55: 12 | M55: 16 | N55: 8 | O55: 48 | P55: 48 | Q55: 64 | R55: 37 | U55: 止痛优选（Repeater） | V55: 短期治痛（Advocator） | W55: 70 | X55: 门诊增加、号源 | Y55: 搭建中青年学术交流平台；结合客户发展规划制定阶段性沟通计划；建立患者随访及病例管理 | Z55: 中青年专家平台；客户学术成长资源；患者管理项目支持；月度学术活动支持
A56: 东南大学附属中大医院 | B56: CORE | C56: 郭怡菁 | D56: 神经内科 | E56: 头痛 | F56: A | G56: 是 | H56: 是 | I56: 是 | J56: 头痛专诊 | K56: 4 | L56: 8 | M56: 12 | N56: 44 | O56: 24 | P56: 36 | Q56: 16 | R56: 28 | U56: 阶梯治疗（Tryer） | V56: 止痛优选（Repeater） | W56: 50 | X56: 门诊增加、号源 | Y56: 提升现有患者的持续管理及复诊转化；头痛患者推荐头痛专家门诊 | Z56: 每月2-3场会议，psr协助随访
A57: 东南大学附属中大医院 | B57: CORE | C57: 张正生 | D57: 神经内科 | E57: 脑血管 | F57: B | G57: 是 | H57: 是 | I57: 是 | J57: 无专诊设置 | K57: 0 | L57: 12 | M57: 12 | N57: 0 | O57: 1 | P57: 0 | Q57: 8 | R57: 12 | U57: 阶梯治疗（Tryer） | V57: 止痛优选（Repeater） | W57: 4 | X57: 诊疗路径识别 | Y57: 探索脑血管病患者中的头痛相关诊疗需求 | Z57: 头痛专病管理经验；脑血管病、头痛跨领域资源
A58: 东南大学附属中大医院 | B58: CORE | C58: 蔡文君 | D58: 耳鼻喉科 | E58: 头晕/眩晕 | F58: C | G58: 是 | H58: 否 | I58: 是 | J58: 头晕/眩晕专诊 | K58: 8 | L58: 0 | M58: 8 | N58: 1 | O58: 0 | P58: 0 | Q58: 0 | R58: 3 | U58: 阶梯治疗（Tryer） | V58: 止痛优选（Repeater） | W58: 20 | X58: 诊疗路径识别 | Y58: 提高vm诊断率；共识vm合并眩晕耳鸣患者画像 | Z58: VM诊断相关学术活动
A59: 东南大学附属中大医院 | B59: CORE | C59: 钱方媛 | D59: 神经内科 | E59: 脑血管 | F59: B | G59: 是 | H59: 否 | I59: 否 | J59: 无专诊设置 | K59: 0 | L59: 12 | M59: 12 | N59: 0 | O59: 20 | P59: 5 | Q59: 2 | R59: 1 | U59: 阶梯治疗（Tryer） | V59: 止痛优选（Repeater） | W59: 0
A60: 东南大学附属中大医院 | B60: CORE | C60: 谢春明 | D60: 神经内科 | E60: 脑血管 | F60: B | G60: 是 | H60: 是 | I60: 否 | J60: 无专诊设置 | K60: 0 | L60: 12 | M60: 12 | N60: 0 | O60: 0 | P60: 0 | Q60: 0 | R60: 0 | U60: 不管不治（Freezer） | V60: 阶梯治疗（Tryer） | W60: 4 | X60: 门诊增加、诊疗路径识别 | Y60: 建立更稳定的客户沟通节奏，持续挖掘头痛诊疗机会 | Z60: 协访；重点客户学术资源；区域专家支持
A61: 东南大学附属中大医院 | B61: CORE | C61: 袁宝玉 | D61: 神经内科 | E61: 脑血管 | F61: B | G61: 是 | H61: 否 | I61: 是 | J61: 无专诊设置 | K61: 0 | L61: 8 | M61: 8 | N61: 0 | O61: 0 | P61: 0 | Q61: 0 | R61: 0 | U61: 不管不治（Freezer） | V61: 阶梯治疗（Tryer） | W61: 4 | X61: 门诊增加、诊疗路径识别 | Y61: 加强头痛患者筛查及鉴别诊断意识 | Z61: 头痛前沿科学内容；患者管理项目
A62: 东南大学附属中大医院 | B62: CORE | C62: 陆玲 | D62: 耳鼻喉科 | E62: 头晕/眩晕 | F62: C | G62: 是 | H62: 是 | I62: 是 | J62: 无专诊设置 | K62: 0 | L62: 12 | M62: 12 | N62: 20 | O62: 4 | P62: 4 | Q62: 20 | R62: 0 | U62: 不管不治（Freezer） | V62: 阶梯治疗（Tryer） | W62: 20 | X62: 诊疗路径识别 | Y62: 门诊识别耳蜗型和前庭性偏头痛，提高诊断率 | Z62: VM专病建设经验、VM学术活动
A63: 东南大学附属中大医院 | B63: CORE | C63: 丁小琼 | D63: 耳鼻喉科 | E63: 头晕/眩晕 | F63: C | G63: 是 | H63: 是 | I63: 是 | J63: 无专诊设置 | K63: 0 | L63: 12 | M63: 12 | N63: 0 | O63: 9 | P63: 0 | Q63: 4 | R63: 0 | U63: 不管不治（Freezer） | V63: 阶梯治疗（Tryer） | W63: 20 | X63: 诊疗路径识别 | Y63: 加强耳鼻喉科头晕患者中的偏头痛识别 | Z63: 耳鼻喉-神经内科跨科室平台；VM学术活动
A64: 东南大学附属中大医院 | B64: CORE | C64: 任庆国 | D64: 神经内科 | E64: 脑血管 | F64: B | G64: 否 | H64: 否 | I64: 是 | J64: 无专诊设置 | K64: 0 | L64: 8 | M64: 8 | N64: 0 | O64: 0 | P64: 0 | Q64: 1 | R64: 0 | U64: 不管不治（Freezer） | V64: 阶梯治疗（Tryer） | W64: 2 | X64: 门诊增加、诊疗路径识别 | Y64: 了解客户临床诊疗痛点，寻找学术沟通切入点 | Z64: 典型患者画像工具；指南/共识；正面病例故事
A65: 东南大学附属中大医院 | B65: CORE | C65: 李晓莉 | D65: 神经内科 | E65: 脑血管 | F65: B | G65: 是 | H65: 否 | I65: 否 | J65: 无专诊设置 | K65: 0 | L65: 8 | M65: 8 | N65: 0 | O65: 4 | P65: 0 | Q65: 0 | R65: 0 | U65: 不管不治（Freezer） | V65: 阶梯治疗（Tryer） | W65: 2 | X65: 诊疗路径识别 | Y65: 提高拜访频率、提高诊断率 | Z65: 典型患者画像工具；正反馈病例集
A66: 江苏省人民医院 | B66: TOP | C66: 王登元 | D66: 耳鼻喉科 | E66: 头晕/眩晕 | F66: C | G66: 是 | H66: 是 | I66: 是 | J66: 无专诊设置 | K66: 0 | L66: 12 | M66: 12 | N66: 388 | O66: 400 | P66: 412 | Q66: 480 | R66: 536 | U66: 治痛管理大师（Super Ambassador） | V66: 治痛管理大师（Super Ambassador） | W66: 600 | X66: 门诊号源增加；dot延长（随访），提高正反馈 | Y66: 助力沟通恢复门诊号源；长病程管理，敦促患者随访，增强客户用药信心 | Z66: 月2-3场会议，psr协助随访
A67: 江苏省人民医院 | B67: TOP | C67: 燕兰云 | D67: 神经内科 | E67: 头痛眩晕 | F67: C | G67: 是 | H67: 是 | I67: 是 | J67: 痛晕专诊 | K67: 4 | L67: 8 | M67: 12 | N67: 200 | O67: 244 | P67: 288 | Q67: 112 | R67: 516 | U67: 治痛管理大师（Super Ambassador） | V67: 治痛管理大师（Super Ambassador） | W67: 500 | X67: 中青年平台建设；客户发展规划；完善患者管理及随访 | Y67: 搭建中青年学术交流平台；结合客户发展规划制定阶段性沟通计划；建立患者随访及病例管理 | Z67: 齐恒致远平台搭建；客户学术成长资源；患者管理项目支持；MDT联动
A68: 江苏省人民医院 | B68: TOP | C68: 顾萍 | D68: 神经内科 | E68: 头痛 | F68: A | G68: 是 | H68: 是 | I68: 是 | J68: 头痛专诊 | K68: 4 | L68: 8 | M68: 12 | N68: 256 | O68: 216 | P68: 220 | Q68: 240 | R68: 168 | U68: 治痛管理（Ambassador） | V68: 治痛管理（Ambassador） | W68: 200 | X68: coe卫健委项目；dot延长，提高复诊率；患者管理（随访） | Y68: coe专家评审会议推进；患者随访管理 | Z68: coe会议支持；患者管理项目支持
A69: 江苏省人民医院 | B69: TOP | C69: 董欣 | D69: 神经内科 | E69: 头痛/眩晕 | F69: C | G69: 是 | H69: 是 | I69: 是 | J69: 痛晕专诊 | K69: 4 | L69: 4 | M69: 8 | N69: 84 | O69: 80 | P69: 20 | Q69: 100 | R69: 56 | U69: 止痛优选（Repeater） | V69: 短期治痛（Advocator） | W69: 80 | X69: 加强头痛患者筛查及鉴别诊断意识 | Y69: 患者画像梳理；典型病例整理；围绕临床难点开展针对性交流 | Z69: 头痛亚专科建设经验；中青年平台的加入；讲者级别升级
A70: 江苏省人民医院 | B70: TOP | C70: 曾彦英 | D70: 神经内科 | E70: 头晕/眩晕 | F70: C | G70: 是 | H70: 是 | I70: 是 | J70: 无专诊设置 | K70: 0 | L70: 12 | M70: 12 | N70: 68 | O70: 100 | P70: 84 | Q70: 52 | R70: 44 | U70: 止痛优选（Repeater） | V70: 短期治痛（Advocator） | W70: 80 | X70: 进一步提升客户对老年门头晕患者筛查及鉴别诊断的关注度 | Y70: 病例整理；病例交流；强化患者识别及鉴别诊断思路 | Z70: 协访；典型病例医学支持；LB/GD活动
A71: 江苏省人民医院 | B71: TOP | C71: 史兆春 | D71: 神经内科 | E71: 脑血管 | F71: B | G71: 是 | H71: 是 | I71: 是 | J71: 无专诊设置 | K71: 0 | L71: 12 | M71: 12 | N71: 8 | O71: 20 | P71: 8 | Q71: 12 | R71: 32 | U71: 止痛优选（Repeater） | V71: 止痛优选（Repeater） | W71: 40 | X71: 提高拜访频率、提高诊断率 | Y71: 增加拜访频率理，共识患者画像 | Z71: pim覆盖；脑血管病合并头痛跨领域会议
... A235: 南通大学附属医院 | B235: CORE | C235: 赵映红 | D235: 神经内科 | E235: 脑血管 | F235: B | G235: 是 | H235: 否 | I235: 是 | J235: 无专诊设置 | K235: 0 | L235: 10 | M235: 10 | N235: 4 | O235: 0 | P235: 0 | Q235: 0 | R235: 0 | U235: 不管不治（Freezer） | V235: 阶梯治疗（Tryer） | W235: 12 | X235: 分层治疗方案传递，对中高频患者以及偏头痛合并心血管疾病的患者，偏头痛药物使用的禁忌，传递足量足疗程治疗方案 | Y235: 传递心脑血管风险偏头痛患者的识别方法，使其认识到此类患者应优先选用瑞美吉泮（CGRP受体拮抗剂）进行急性治疗，而非一律从NSAIDs/曲坦起步，并扩大适应证内患者覆盖。 【诊疗路径】建立CGRP受体拮抗剂与偏头痛/头痛诊疗的有效关联，从零搭建相关患者的识别与处理意识；对适合患者启动治痛管理随访，记录MMD变化以强化观念。 安排参加科室会/城市沙龙，借助区域KOL观念辐射逐步实现从0到1的开发。 | Z235: DM/RM/RPM协同拜访资源与区域学术会议名额。 患者教育材料与治痛管理工具包（随访表、MMD记录卡），支撑长期管理落地。 标杆医生培育资源：城市会/区域会讲者平台与青年医生带教支持
A236: 南通大学附属医院 | B236: CORE | C236: 秦毅彬 | D236: 疼痛科 | E236: 疼痛 | F236: D | G236: 是 | H236: 否 | I236: 否 | J236: 疼痛专诊 | K236: 4 | L236: 4 | M236: 8 | N236: 0 | O236: 0 | P236: 0 | Q236: 0 | R236: 0 | W236: 12 | X236: 传递目前疼痛科治疗现状，以及外部专家使用方案。分层治疗方案传递，使用瑞美足量足疗程治疗3-6月，可逆转疾病进展。 | Y236: 每次诊前拜访，手术评估无需手术，高频/中频患者，使用瑞美足量足疗程治疗3-6月，可逆转疾病进展。术后出院患者，可出院带药，预防急性发作 | Z236: PIM CALL/LB 患者教育材料与治痛管理工具包（随访表、MMD记录卡），支撑长期管理落地。 标杆医生培育资源：城市会/区域会讲者平台与青年医生带教，学会任职，提高影响力
A237: 南通市第一人民医院 | B237: CORE | C237: 董政协 | D237: 神经内科 | E237: 头晕/眩晕 | F237: C | G237: 是 | H237: 是 | I237: 是 | J237: 头晕/眩晕专诊 | K237: 4 | L237: 12 | M237: 16 | N237: 228 | O237: 364 | P237: 312 | Q237: 312 | R237: 368 | U237: 资深治痛管理（Experienced Ambassador） | V237: 治痛管理大师（Super Ambassador） | W237: 500 | X237: 1.头晕专诊4次/月，传递VM五大形态观念，足量足疗程治疗； 2.可依托专诊平台建立VM患者全程管理随访体系，实现疾病病程逆转； 3.作为科室学术标杆，可通过病例分享、科室带教辐射带动神经内科及耳鼻喉科B/C类客户观念提升。 | Y237: 1.每周2次深访，聚焦前庭性偏头痛（反复眩晕+头痛史）的ICHD-3诊断标准与鉴别诊断路径，强化VM患者"急性+预防"全程管理理念，推动治痛管理周期延长至6个月； 2.每次专诊前递送VM最新指南/共识及瑞美吉泮在前庭性偏头痛中的循证证据，目标9月新增VM规范治疗患者8例，其中启动预防性治疗≥3例； 3.协助建立头晕/眩晕专诊患者随访登记系统，记录MMD（每月头痛天数）及眩晕发作频率变化，以真实世界数据强化管理信心； 4.联合科室开展1次"前庭性偏头痛全程管理"病例讨论会，由董政协主任主讲，覆盖神经内科+耳鼻喉科全体目标客户，发挥标杆辐射效应； 5.邀请参与区域学术会议/城市会并争取讲者席位，输出VM诊疗经验，提升区域学术影响力。 | Z237: 1.前庭性偏头痛ICHD-3诊断标准、VM与BPPV/梅尼埃病/最新指南/共识文献； 2.瑞美吉泮在前庭性偏头痛及偏头痛预防性治疗中的循证医学资料包（含2小时无痛率、长期安全性、MMD改善数据）； 3.头晕/眩晕专诊患者随访登记表、MMD记录卡及患者教育手册； 4.区域学术会议/城市会讲者平台与科室病例讨论会学术支持（讲者课件、会议场地、参会激励）； 5.MICS/DM协同拜访资源及上级医院眩晕中心专家会诊/转诊对接。
A238: 南通市第一人民医院 | B238: CORE | C238: 李燕 | D238: 神经内科 | E238: 癫痫 | F238: B | G238: 是 | H238: 是 | I238: 是 | J238: 无专诊设置 | K238: 0 | L238: 8 | M238: 8 | N238: 8 | O238: 16 | P238: 8 | Q238: 8 | R238: 8 | U238: 阶梯治疗（Tryer） | V238: 止痛优选（Repeater） | W238: 30 | X238: 【分层治疗】传递分层治疗方案：针对中高频患者及偏头痛合并心血管疾病的患者，明确药物使用禁忌；同时传递足量足疗程的治疗方案。 | Y238: 1) 传递心脑血管风险偏头痛患者的识别方法，使其认识到此类患者应优先选用瑞美吉泮（CGRP受体拮抗剂）进行急性治疗，而非一律从NSAIDs/曲坦起步，并扩大适应证内患者覆盖； 2) 【诊疗路径】建立CGRP受体拮抗剂与偏头痛/头痛诊疗的有效关联，从零搭建相关患者的识别与处理意识；对适合患者启动治痛管理随访、记录MMD变化以强化观念； 3) 安排参加科室会/城市沙龙，借助区域KOL观念辐射逐步实现从0到1的开发。 | Z238: 【协同拜访】区域学术会议名额，LB召开。 【患者管理】患者教育材料及治痛管理工具包（随访表、MMD记录卡），支撑长期管理落地。 【标杆培育】城市会/区域会讲者平台与青年医生带教支持。
A239: 南通市第一人民医院 | B239: CORE | C239: 朱向阳 | D239: 神经内科 | E239: 头痛 | F239: A | G239: 是 | H239: 否 | I239: 是 | J239: 头痛专诊 | K239: 4 | L239: 12 | M239: 16 | N239: 4 | O239: 4 | P239: 4 | Q239: 4 | R239: 8 | U239: 阶梯治疗（Tryer） | V239: 止痛优选（Repeater） | W239: 50 | X239: 1A类客户但观念仅处于阶梯治疗层级，传递分层治疗观念，中高频患者治疗3-6个月可逆转疾病进展，加速观念提升至止痛优选乃至治痛管理； 2.头痛专诊患者中高频发作（≥4天/月）比例高可推动全程管理模式； | Y239: 1.9月每周1次专诊前拜访，重点传递偏头痛急性期规范治疗理念，强化瑞美吉泮"早期足量、2小时无痛"的临床价值，目标9月处方量提升至30，新增急性治疗患者5例； 2.递送偏头痛对月发作≥4天的患者推动启动足疗程治疗方案， 3.联合董政协主任开展头痛专诊病例交流，学习全程管理经验，目标9月观念提升至止痛优选层级； 5.协助头痛专诊患者随访登记 | Z239: 1.偏头痛急性期及预防性治疗最新指南/共识文献； 2.瑞美吉泮急性+预防双适应证循证医学资料包； 3.244标签及出诊简介标签系统录入支持； 4.头痛专诊患者随访登记表、MMD记录卡及患者教育手册； 5.科室病例交流与学术带教资源。
A240: 南通市第一人民医院 | B240: CORE | C240: 陈蓝 | D240: 神经内科 | E240: 脑血管 | F240: B | G240: 是 | H240: 否 | I240: 是 | J240: 无专诊设置 | K240: 0 | L240: 8 | M240: 8 | N240: 16 | O240: 8 | P240: 12 | Q240: 4 | R240: 4 | U240: 阶梯治疗（Tryer） | V240: 止痛优选（Repeater） | W240: 30 | X240: 【分层治疗】传递分层治疗方案：针对中高频患者及偏头痛合并心血管疾病的患者，明确药物使用禁忌；同时传递足量足疗程的治疗方案。 | Y240: 1) 传递心脑血管风险偏头痛患者的识别方法，使其认识到此类患者应优先选用瑞美吉泮（CGRP受体拮抗剂）进行急性治疗，而非一律从NSAIDs/曲坦起步，并扩大适应证内患者覆盖； 2) 【诊疗路径】建立CGRP受体拮抗剂与偏头痛/头痛诊疗的有效关联，从零搭建相关患者的识别与处理意识；对适合患者启动治痛管理随访、记录MMD变化以强化观念； 3) 安排参加科室会/城市沙龙，借助区域KOL观念辐射逐步实现从0到1的开发。 | Z240: 【协同拜访】DM/RM/RPM协同拜访资源与区域学术会议名额。 【患者管理】患者教育材料及治痛管理工具包（随访表、MMD记录卡），支撑长期管理落地。 【标杆培育】城市会/区域会讲者平台与青年医生带教支持。
A241: 南通市第一人民医院 | B241: CORE | C241: 秦阳 | D241: 耳鼻喉科 | E241: 头晕/眩晕 | F241: C | G241: 是 | H241: 否 | I241: 是 | J241: 无专诊设置 | K241: 0 | L241: 8 | M241: 8 | N241: 0 | O241: 0 | P241: 0 | Q241: 0 | R241: 4 | U241: 阶梯治疗（Tryer） | V241: 止痛优选（Repeater） | W241: 30 | X241: 【标签/专诊/号源】门诊简介暂无标签，可通过完善标签、增设或扩容专诊来提高患者归拢率。 【诊疗观念】聚焦前庭性偏头痛（反复眩晕+头痛史）的识别，与BPPV、梅尼埃病做好鉴别；传递足量足疗程观念，并强调患者长期管理的必要性。 | Y241: 1) 每周2次深访，【专诊号源/标签】协同门诊推动开设耳鼻喉科眩晕专诊或增加专诊，补全标签、扩充号源以承接更多患者； 2) 聚焦前庭性偏头痛（反复眩晕+头痛史）的识别，与BPPV、梅尼埃病鉴别；对前庭性偏头痛患者定位瑞美吉泮在急性与频率管理中的价值，并启动治痛管理随访、记录MMD变化以强化观念； 3) 邀请参与区域学术会议/科室沙龙，争取讲者/病例分享机会，带动眩晕/耳鼻喉组内观念。 | Z241: 【协同拜访】DM/RM/RPM协同拜访资源与区域学术会议名额。 【患者管理】患者教育材料及治痛管理工具包（随访表、MMD记录卡），支撑长期管理落地。 【标杆培育】城市会/区域会讲者平台与青年医生带教支持。
A242: 南通市第一人民医院 | B242: CORE | C242: 朱连海 | D242: 神经内科 | E242: 脑血管 | F242: B | G242: 是 | H242: 否 | I242: 是 | J242: 无专诊设置 | K242: 0 | L242: 8 | M242: 8 | N242: 0 | O242: 0 | P242: 0 | Q242: 4 | R242: 0 | U242: 不管不治（Freezer） | V242: 阶梯治疗（Tryer） | W242: 12 | X242: 1.从"不管不治"向"阶梯治疗"破冰，传递分层治疗观念，中高频患者治疗3-6个月可逆转疾病进展，加速观念提升至止痛优选乃至治痛管理； 2.伴心脑血管风险的偏头痛患者中，NSAIDs/曲坦类存在禁忌，CGRP受体拮抗剂具有差异化优势。 | Y242: 1.9月安排1次深访，分析针对性解决顾虑； 2.每两周1次破冰拜访，传递CGRP受体拮抗剂与偏头痛规范诊疗的关联，逐步建立处方信心； 3.提供瑞美吉泮快速起效及心血管安全性数据，配合典型病例分享，目标9月重新实现首方并稳定至≥2例患者； 4.协助在脑血管门诊建立头痛患者快速筛查意识，对中重度偏头痛患者推荐规范治疗； 5.邀请参加科室病例讨论会，借助KOL观念辐射逐步实现从0到1的开发。 | Z242: 1.偏头痛规范诊疗入门资料及CGRP受体拮抗剂作用机制科普； 2.瑞美吉泮快速起效及心血管安全性临床数据速查卡； 3.典型偏头痛治疗病例集（含脑血管共病案例）； 4.门诊头痛患者识别筛查工具； 5.MICS/DM协同破冰拜访资源及科室病例讨论会参会名额。
A243: 南通市第一人民医院 | B243: CORE | C243: 吴昊 | D243: 耳鼻喉科 | E243: 头晕/眩晕 | F243: C | G243: 是 | H243: 是 | I243: 是 | J243: 无专诊设置 | K243: 0 | L243: 8 | M243: 8 | N243: 0 | O243: 0 | P243: 0 | Q243: 0 | R243: 0 | U243: 不管不治（Freezer） | V243: 阶梯治疗（Tryer） | W243: 12 | X243: 【标签/专诊/号源】门诊简介暂无标签，可通过完善标签、增设或扩容专诊来提高患者归拢率。 【诊疗观念】聚焦前庭性偏头痛（反复眩晕+头痛史）的识别，与BPPV、梅尼埃病做好鉴别；传递足量足疗程观念，并强调患者长期管理的必要性。 | Y243: 1) 每周2次深访，【专诊号源/标签】协同门诊推动开设耳鼻喉科眩晕专诊或增加专诊，补全标签、扩充号源以承接更多患者； 2) 聚焦前庭性偏头痛（反复眩晕+头痛史）的识别，与BPPV、梅尼埃病鉴别；对前庭性偏头痛患者定位瑞美吉泮在急性与频率管理中的价值，并启动治痛管理随访、记录MMD变化以强化观念； 3) 邀请参与区域学术会议/科室沙龙，争取讲者/病例分享机会，带动眩晕/耳鼻喉组内观念。 | Z243: 【协同拜访】DM/RM/RPM协同拜访资源与区域学术会议名额。 【患者管理】患者教育材料及治痛管理工具包（随访表、MMD记录卡），支撑长期管理落地。 【标杆培育】城市会/区域会讲者平台与青年医生带教支持。
A244: 南通市第一人民医院 | B244: CORE | C244: 杨家伟 | D244: 神经内科 | E244: 头痛 | F244: A | G244: 是 | H244: 否 | I244: 是 | J244: 头痛专诊 | K244: 4 | L244: 4 | M244: 8 | N244: 20 | O244: 0 | P244: 0 | Q244: 0 | R244: 0 | U244: 不管不治（Freezer） | V244: 阶梯治疗（Tryer） | W244: 30 | X244: 【分层治疗】传递分层治疗方案：针对中高频患者及偏头痛合并心血管疾病的患者，明确药物使用禁忌；同时传递足量足疗程的治疗方案。 | Y244: 1) 传递心脑血管风险偏头痛患者的识别方法，使其认识到此类患者应优先选用瑞美吉泮（CGRP受体拮抗剂）进行急性治疗，而非一律从NSAIDs/曲坦起步，并扩大适应证内患者覆盖； 2) 【诊疗路径】建立CGRP受体拮抗剂与偏头痛/头痛诊疗的有效关联，从零搭建相关患者的识别与处理意识；对适合患者启动治痛管理随访、记录MMD变化以强化观念； 3) 安排参加科室会/城市沙龙，借助区域KOL观念辐射逐步实现从0到1的开发。 | Z244: 【协同拜访】区域学术会议名额，LB召开。 【患者管理】患者教育材料及治痛管理工具包（随访表、MMD记录卡），支撑长期管理落地。 【标杆培育】城市会/区域会讲者平台与青年医生带教支持。
A245: 南通市第一人民医院 | B245: CORE | C245: 曹志勇 | D245: 神经内科 | E245: 脑血管 | F245: B | G245: 是 | H245: 否 | I245: 否 | J245: 无专诊设置 | K245: 0 | L245: 4 | M245: 4 | N245: 4 | O245: 4 | P245: 0 | Q245: 0 | R245: 0 | U245: 不管不治（Freezer） | V245: 阶梯治疗（Tryer） | W245: 20 | X245: 1.出诊简介无头痛/眩晕标签，头痛共病患者识别率极低； 2.从"不管不治"向"阶梯治疗"破冰，需建立CGRP受体拮抗剂与偏头痛诊疗的基本关联； 3.每月4次门诊，患者基数有限但仍存在从0到1的开发机会； 4.伴心脑血管风险的偏头痛患者中，CGRP受体拮抗剂较NSAIDs/曲坦类具有安全性优势。 | Y245: 1.9月每两周1次破冰拜访，传递CGRP受体拮抗剂与偏头痛规范诊疗的关联，重点沟通伴心脑血管风险患者的治疗选择； 2.提供瑞美吉泮心血管安全性数据及典型病例，建立基础处方信心，目标9月实现首方≥1例患者； 3.协助推动出诊简介头痛/眩晕标签完善，提升院内系统识别度； 4.邀请参加科室病例讨论会，借助KOL观念辐射逐步实现从0到1的开发。 | Z245: 1.偏头痛规范诊疗入门资料及CGRP受体拮抗剂作用机制科普； 2.瑞美吉泮心血管安全性临床数据速查卡； 3.典型偏头痛治疗病例集（含脑血管共病案例）； 4.出诊简介标签系统录入支持； 5.DM协同破冰拜访资源及科室病例讨论会参会名额。
A246: 南通市第一人民医院 | B246: CORE | C246: 陆珍辉 | D246: 神经内科 | E246: 脑血管 | F246: B | G246: 是 | H246: 否 | I246: 否 | J246: 无专诊设置 | K246: 0 | L246: 4 | M246: 4 | N246: 0 | O246: 0 | P246: 0 | Q246: 0 | R246: 0 | U246: 不管不治（Freezer） | V246: 阶梯治疗（Tryer） | W246: 12 | X246: 【分层治疗】传递分层治疗方案：针对中高频患者及偏头痛合并心血管疾病的患者，明确药物使用禁忌；同时传递足量足疗程的治疗方案。 | Y246: 1) 传递心脑血管风险偏头痛患者的识别方法，使其认识到此类患者应优先选用瑞美吉泮（CGRP受体拮抗剂）进行急性治疗，而非一律从NSAIDs/曲坦起步，并扩大适应证内患者覆盖； 2) 【诊疗路径】建立CGRP受体拮抗剂与偏头痛/头痛诊疗的有效关联，从零搭建相关患者的识别与处理意识；对适合患者启动治痛管理随访、记录MMD变化以强化观念； 3) 安排参加科室会/城市沙龙，借助区域KOL观念辐射逐步实现从0到1的开发。 | Z246: 【协同拜访】DM/RM/RPM协同拜访资源与区域学术会议名额。 【患者管理】患者教育材料及治痛管理工具包（随访表、MMD记录卡），支撑长期管理落地。 【标杆培育】城市会/区域会讲者平台与青年医生带教支持。
A247: 南通市第一人民医院 | B247: CORE | C247: 郭啸鸣 | D247: 神经内科 | E247: 脑血管 | F247: B | G247: 是 | H247: 否 | I247: 否 | J247: 无专诊设置 | K247: 0 | L247: 4 | M247: 4 | N247: 0 | O247: 0 | P247: 0 | Q247: 0 | R247: 0 | U247: 不管不治（Freezer） | V247: 阶梯治疗（Tryer） | W247: 12 | X247: 1.出诊简介无头痛/眩晕标签，头痛共病患者处于完全未开发状态； 2.从"不管不治"向"阶梯治疗"破冰，需建立偏头痛规范诊疗的基本认知； 3.每月4次门诊，需精准定位伴头痛症状且适合CGRP受体拮抗剂的患者； 4.可借助科室整体学术氛围提升，通过KOL辐射带动观念转变。 | Y247: 1.9月每两周1次破冰拜访，传递偏头痛规范诊疗理念及CGRP受体拮抗剂作用机制，重点关注伴心脑血管风险患者的治疗选择； 2.提供瑞美吉泮临床数据及典型病例，建立基础处方信心，目标9月实现首方≥1例患者； 3.协助推动出诊简介头痛/眩晕标签完善； 4.邀请参加科室病例讨论会，借助KOL观念辐射逐步实现从0到1的开发。 | Z247: 1.偏头痛规范诊疗入门资料及CGRP受体拮抗剂作用机制科普； 2.瑞美吉泮临床数据速查卡（疗效+安全性）； 3.典型偏头痛治疗病例集； 4.出诊简介标签系统录入支持； 5.DM协同破冰拜访资源及科室病例讨论会参会名额。
A248: 南通市第一人民医院 | B248: CORE | C248: 邵良 | D248: 神经内科 | E248: 脑血管 | F248: B | G248: 是 | H248: 否 | I248: 是 | J248: 无专诊设置 | K248: 0 | L248: 4 | M248: 4 | N248: 0 | O248: 0 | P248: 0 | Q248: 0 | R248: 0 | U248: 不管不治（Freezer） | V248: 阶梯治疗（Tryer） | W248: 12 | X248: 1.出诊简介已含头痛/眩晕标签，但尚未转化为首方； 2.从"不管不治"向"阶梯治疗"破冰， 3.中高频偏头痛患者中，CGRP受体拮抗剂具有差异化治疗优势。 | Y248: 1.9月每两周1次破冰拜访，利用已有头痛标签基础，传递偏头痛规范诊疗理念及CGRP受体拮抗剂在伴心脑血管风险患者中的优先选择依据； 2.提供瑞美吉泮心血管安全性数据及典型病例，目标9月实现首方≥1例患者； 3.协助在门诊中建立头痛患者快速筛查意识，对中重度偏头痛患者推荐规范治疗； 4.邀请参加科室病例讨论会，借助KOL观念辐射推动观念提升。 | Z248: 1.偏头痛规范诊疗入门资料及CGRP受体拮抗剂作用机制科普； 2.典型偏头痛治疗病例集（含脑血管共病案例）； 3.门诊头痛患者识别筛查工具； 4.DM协同破冰拜访资源及科室病例讨论会参会名额。
... A260: 青岛大学附属医院 | B260: CORE | C260: 付涛 | D260: 耳鼻喉科 | E260: 头晕/眩晕 | F260: C | G260: 是 | H260: 否 | I260: 是 | J260: 无专诊设置 | K260: 0 | L260: 16 | M260: 16 | N260: 0 | O260: 0 | P260: 0 | Q260: 0 | R260: 0 | U260: 不管不治（Freezer） | V260: 不管不治（Freezer） | W260: 0 | X260: 朱晓宁主任学会共同发起，借助学会及流调加强大客户管理，沟通医院临采提单 | Y260: 对流调及学会事宜深入沟通，客情维护 | Z260: Q4三方会主持1
A261: 青岛大学附属医院 | B261: CORE | C261: 纪彩丽 | D261: 耳鼻喉科 | E261: 头晕/眩晕 | F261: C | G261: 是 | H261: 否 | I261: 是 | J261: 头晕/眩晕专诊 | K261: 4 | L261: 16 | M261: 16 | N261: 0 | O261: 0 | P261: 0 | Q261: 0 | R261: 0 | U261: 不管不治（Freezer） | V261: 不管不治（Freezer） | W261: 20 | X261: 已参加线下会议，对于产品机制较为认可，但在诊断方面存在提升空间 | Y261: 目前有锁定患者，跟进破冰后，持续融动
A262: 青岛大学附属医院 | B262: CORE | C262: 李慎玲 | D262: 耳鼻喉科 | E262: 头晕/眩晕 | F262: C | G262: 是 | H262: 否 | I262: 是 | J262: 无专诊设置 | K262: 0 | L262: 16 | M262: 16 | N262: 0 | O262: 0 | P262: 0 | Q262: 0 | R262: 0 | U262: 不管不治（Freezer） | V262: 不管不治（Freezer） | W262: 20 | X262: 参加神内耳鼻喉宴请，对于眩晕较感兴趣 | Y262: 利用小圈子影响观念，先融动破传递病例正反馈 | Z262: 三方会1/PO1
A263: 青岛大学附属医院 | B263: CORE | C263: 赵仁亮 | D263: 神经内科 | E263: 头晕/眩晕 | F263: C | G263: 是 | H263: 否 | I263: 是 | J263: 无专诊设置 | K263: 0 | L263: 16 | M263: 16 | N263: 0 | O263: 0 | P263: 0 | Q263: 0 | R263: 0 | U263: 不管不治（Freezer） | V263: 不管不治（Freezer） | W263: 20 | X263: 眩晕门诊，是青医最早开始做眩晕的客户 | Y263: 小圈子宴请融动，暂时不参会 | Z263: 暂无
A264: 青岛大学附属医院 | B264: CORE | C264: 张栩 | D264: 精神/心理科 | E264: 抑郁焦虑 | F264: D | G264: 是 | H264: 否 | I264: 否 | J264: 无专诊设置 | K264: 0 | L264: 16 | M264: 16 | N264: 0 | O264: 0 | P264: 0 | Q264: 0 | R264: 0 | U264: 不管不治（Freezer） | V264: 不管不治（Freezer） | W264: 20 | X264: 参加过青医质控线下会议，对于产品较为认可，积极推荐中 | Y264: 抑郁焦虑共病患者，病例反馈，科室内老师已有破冰，持续融动 | Z264: 暂无
A265: 青岛大学附属医院 | B265: CORE | C265: 宋敬卉 | D265: 神经内科 | E265: 脑血管 | F265: B | G265: 否 | H265: 否 | I265: 是 | J265: 无专诊设置 | K265: 0 | L265: 8 | M265: 8 | N265: 0 | O265: 0 | P265: 0 | Q265: 0 | R265: 0 | U265: 不管不治（Freezer） | V265: 不管不治（Freezer） | W265: 0 | X265: 自身是偏头痛患者，对于产品疗效很认可 | Y265: 病房主任，通过GD会议覆盖 | Z265: 暂无
A266: 青岛大学附属医院 | B266: CORE | C266: 王亚男 | D266: 神经内科 | E266: 脑血管 | F266: B | G266: 是 | H266: 否 | I266: 是 | J266: 无专诊设置 | K266: 0 | L266: 16 | M266: 16 | N266: 0 | O266: 0 | P266: 0 | Q266: 0 | R266: 0 | U266: 不管不治（Freezer） | V266: 不管不治（Freezer） | W266: 0 | X266: 门诊偏头痛患者较少，既往无处方经验；但合作意愿度较高 | Y266: 夜访跟进，明确患者画像，利用病例正反馈，融动处方破冰 | Z266: 暂无
A267: 青岛市精神卫生中心 | B267: CORE | C267: 曲春晖 | D267: 精神/心理科 | E267: 抑郁焦虑 | F267: D | G267: 是 | H267: 是 | I267: 否 | J267: 无专诊设置 | K267: 0 | L267: 16 | M267: 16 | N267: 40 | O267: 56 | P267: 40 | Q267: 28 | R267: 56 | U267: 止痛优选（Repeater） | V267: 止痛优选（Repeater） | W267: 70 | X267: 融动加入头痛专诊，提升偏头痛诊断率，提高患者归拢率 | Y267: 1、参加线上PO会议，同步其他区域优质病例，传递需要尽早治疗，足疗程治疗 2、每周三拜访复盘近期处方患者，收集足量足疗程病例_x000b_3、每月一次家访，增强客情 | Z267: po会1季度1-2场，GD会议覆盖
A268: 青岛市精神卫生中心 | B268: CORE | C268: 孙波 | D268: 精神/心理科 | E268: 抑郁焦虑 | F268: D | G268: 是 | H268: 是 | I268: 否 | J268: 头痛专诊 | K268: 4 | L268: 24 | M268: 28 | N268: 0 | O268: 12 | P268: 8 | Q268: 12 | R268: 12 | U268: 阶梯治疗（Tryer） | V268: 止痛优选（Repeater） | W268: 70 | X268: 增加头痛专诊量，提升偏头痛诊断率，提高患者归拢率，增加门诊标签 | Y268: 1、开展GD会议，学习交流其他区域优质病例，方案，学习足量足疗程治疗，尽早治疗_x000b_2、做好患者管理，每周两次诊后拜访，收集正反馈病例，增强用药信心 | Z268: 三方会1季度1-2场，GD会议覆盖
A269: 青岛市精神卫生中心 | B269: CORE | C269: 殷军波 | D269: 精神/心理科 | E269: 抑郁焦虑 | F269: D | G269: 是 | H269: 是 | I269: 否 | J269: 头痛专诊 | K269: 4 | L269: 4 | M269: 8 | N269: 0 | O269: 0 | P269: 0 | Q269: 0 | R269: 0 | U269: 不管不治（Freezer） | V269: 阶梯治疗（Tryer） | W269: 30 | X269: 增加头痛专诊量，提升偏头痛诊断率，提高患者归拢率，增加门诊标签 | Y269: 1、邀请参加GD会议，学习交流其他区域优质病例，方案，学习足量足疗程治疗，尽早治疗_x000b_2、做好患者管理，每周两次诊后拜访，收集正反馈病例，增强用药信心 | Z269: 三方会1季度1-2场，GD会议覆盖
A270: 青岛市精神卫生中心 | B270: CORE | C270: 刘淇丰 | D270: 精神/心理科 | E270: 抑郁焦虑 | F270: D | G270: 否 | H270: 是 | I270: 否 | J270: 头痛专诊 | K270: 4 | L270: 4 | M270: 8 | N270: 0 | O270: 0 | P270: 0 | Q270: 0 | R270: 0 | U270: 不管不治（Freezer） | V270: 阶梯治疗（Tryer） | W270: 10 | X270: 增加头痛专诊量，提升偏头痛诊断率，提高患者归拢率，增加门诊标签 | Y270: 1、邀请参加GD会议，学习交流其他区域优质病例，方案，学习足量足疗程治疗，尽早治疗_x000b_2、做好患者管理，每周两次诊后拜访，收集正反馈病例，增强用药信心 | Z270: GD会议覆盖
A271: 青岛市精神卫生中心 | B271: CORE | C271: 石少波 | D271: 精神/心理科 | E271: 抑郁焦虑 | F271: D | G271: 是 | H271: 是 | I271: 否 | J271: 无专诊设置 | K271: 0 | L271: 14 | M271: 14 | N271: 0 | O271: 4 | P271: 0 | Q271: 0 | R271: 0 | U271: 不管不治（Freezer） | V271: 阶梯治疗（Tryer） | W271: 10 | X271: 融动加入头痛专诊，提升偏头痛诊断率，提高患者归拢率 | Y271: 1、邀请参加GD会议，学习交流其他区域优质病例，方案，学习足量足疗程治疗，尽早治疗_x000b_2、做好患者管理，每周两次诊后拜访，收集正反馈病例，增强用药信心 | Z271: 三方会1季度1-2场，GD会议覆盖
A272: 青岛市精神卫生中心 | B272: CORE | C272: 范勇 | D272: 精神/心理科 | E272: 抑郁焦虑 | F272: D | G272: 是 | H272: 是 | I272: 否 | J272: 无专诊设置 | K272: 0 | L272: 15 | M272: 15 | N272: 20 | O272: 8 | P272: 0 | Q272: 8 | R272: 0 | U272: 不管不治（Freezer） | V272: 阶梯治疗（Tryer） | W272: 30 | X272: 融动加入头痛专诊，提升偏头痛诊断率，提高患者归拢率 | Y272: 1、邀请参加GD会议，学习交流其他区域优质病例，方案，学习足量足疗程治疗，尽早治疗_x000b_2、做好患者管理，每周两次诊后拜访，收集正反馈病例，增强用药信心 | Z272: 三方会1季度1-2场，GD会议覆盖
A273: 青岛市精神卫生中心 | B273: CORE | C273: 孙辰辉 | D273: 精神/心理科 | E273: 抑郁焦虑 | F273: D | G273: 是 | H273: 是 | I273: 否 | J273: 头痛专诊 | K273: 1 | L273: 4 | M273: 5 | N273: 0 | O273: 0 | P273: 0 | Q273: 0 | R273: 0 | U273: 不管不治（Freezer） | V273: 阶梯治疗（Tryer） | W273: 10 | X273: 增加头痛专诊量，提升偏头痛诊断率，提高患者归拢率，增加门诊标签 | Y273: 1、邀请参加GD会议，学习交流其他区域优质病例，方案，学习足量足疗程治疗，尽早治疗_x000b_2、做好患者管理，每周两次诊后拜访，收集正反馈病例，增强用药信心 | Z273: 三方会1季度1-2场，GD会议覆盖
... A301: 青岛市市立医院 | B301: CORE | C301: 宗煜 | D301: 神经内科 | E301: 脑血管 | F301: B | G301: 是 | H301: 否 | I301: 是 | J301: 无专诊设置 | K301: 0 | L301: 8 | M301: 8 | N301: 16 | O301: 0 | P301: 0 | Q301: 12 | R301: 0 | U301: 不管不治（Freezer） | V301: 阶梯治疗（Tryer） | W301: 10 | X301: 提升偏头痛诊断率，提高患者归拢率，拓展患者画像 | Y301: 1、与耳鼻喉科开展学术会议交流，突破vm患者_x000b_2、拓展患者类型（低中高CM/MOH,月偏），借助学术会议，实现新拓展画像破冰 10、门诊前提醒诊后门诊当天复盘患者，加强足疗程理念 | Z301: 三方会1场/季度
A302: 青岛市西海岸医院 | B302: CORE | C302: 张亮 | D302: 神经内科 | E302: 头痛 | F302: A | G302: 是 | H302: 是 | I302: 是 | J302: 头痛专诊 | K302: 4 | L302: 4 | M302: 8 | N302: 184 | O302: 176 | P302: 168 | Q302: 168 | R302: 180 | S302: 132 | U302: 治痛管理（Ambassador） | V302: 资深治痛管理（Experienced Ambassador） | W302: 220 | X302: 增加门诊（8月门诊减半直接影响销量），门诊宣传，诊疗路径mdt院内交流 | Y302: 1、沟通周天增加门诊半天，跟进头痛专诊运行，PO会区域间交流资深治痛管理理念 2、邀请作为院内学术分享讲者，输出头痛规范化诊疗结合疼痛科3、专诊内使用患者筛查工具和问卷，进一步挖掘标签患者，寻找增量机会点 | Z302: 头痛规范化诊疗循证资料、头痛患者科普宣教物料
A303: 青岛市西海岸医院 | B303: CORE | C303: 李宏 | D303: 神经内科 | E303: 头晕/眩晕 | F303: C | G303: 是 | H303: 是 | I303: 是 | J303: 头晕/眩晕专诊 | K303: 4 | L303: 2 | M303: 6 | N303: 76 | O303: 76 | P303: 72 | Q303: 112 | R303: 96 | S303: 108 | U303: 短期治痛（Advocator） | V303: 治痛管理（Ambassador） | W303: 130 | X303: 观念升级，眩晕门诊规范管理，患者随访 | Y303: 1、会议和眩晕平台学习眩晕合并头痛共病（VM）诊疗理念，推动从短期对症治疗转向长期治痛管理；2、在眩晕专诊中识别标签患者，眩晕患者以及头痛患者管理，采用随访平台随访，学习zqx专家的诊疗思路 | Z303: VM临床文献、患者筛查量表，会议平台推荐，眩晕圈层打造
A304: 青岛市西海岸医院 | B304: CORE | C304: 贾春燕 | D304: 神经内科 | E304: 头痛 | F304: A | G304: 是 | H304: 是 | I304: 是 | J304: 无专诊设置 | K304: 0 | L304: 0 | M304: 0 | N304: 16 | O304: 28 | P304: 40 | Q304: 28 | R304: 20 | S304: 4 | U304: 阶梯治疗（Tryer） | V304: 止痛优选（Repeater） | W304: 40 | X304: 观念升级，建立专病门诊（9月），门诊宣传， | Y304: 1、门诊PSR跟诊，挖掘门诊头痛就诊患者标签；2、沟通阶梯治疗之后长期止痛优选的诊疗思路；3、提供临床病例，患者累计和管理 | Z304: 临床资料，学术平台，病例交流机会
A305: 青岛市西海岸医院 | B305: CORE | C305: 孟超 | D305: 疼痛科 | E305: 疼痛 | F305: D | G305: 是 | H305: 是 | I305: 是 | J305: 疼痛专诊 | K305: 1 | L305: 6 | M305: 7 | N305: 28 | O305: 4 | P305: 20 | Q305: 28 | R305: 16 | S305: 12 | U305: 阶梯治疗（Tryer） | V305: 短期治痛（Advocator） | W305: 20 | X305: 观念升级，神经阻滞门诊号源，慢性头痛患者优先 | Y305: 1、神经阻滞专诊重点跟进，关注慢性疼痛头痛患者2、沟通阶梯治疗后短期治痛3、从小样本病例做起，逐步建立用药习惯 | Z305: GD，PO会议
A306: 青岛市西海岸医院 | B306: CORE | C306: 孙秀明 | D306: 疼痛科 | E306: 疼痛 | F306: D | G306: 否 | H306: 否 | I306: 否 | J306: 无专诊设置 | K306: 0 | L306: 6 | M306: 6 | N306: 0 | O306: 12 | P306: 8 | Q306: 0 | R306: 4 | S306: 0 | U306: 阶梯治疗（Tryer） | V306: 阶梯治疗（Tryer） | W306: 12 | X306: 观念升级，专诊规范运营，患者画像描绘 | Y306: 1、出诊时段拜访，筛选慢性疼痛伴头痛病例 2、以阶梯治疗作为切入点，提供简单临床案例，保证连续处方 3、提供制作简短的临床口袋参考卡片 | Z306: 三方会议覆盖，区域交流
A307: 青岛市西海岸医院 | B307: CORE | C307: 滕继军 | D307: 神经内科 | E307: 脑血管 | F307: B | G307: 是 | H307: 否 | I307: 是 | J307: 无专诊设置 | K307: 0 | L307: 4 | M307: 4 | N307: 0 | O307: 0 | P307: 0 | Q307: 0 | R307: 0 | S307: 0 | U307: 不管不治（Freezer） | V307: 止痛优选（Repeater） | W307: 12 | X307: 观念升级，脑血管门诊，脑血管合并头痛，具备潜在患者机会 | Y307: 1、优先用真实临床病例做切入，改变“不管不治”观念 2、先筛选合适轻症患者尝试，向止痛优选观念靠拢3、脑血管会议区域会交流 | Z307: 三方会议覆盖，区域交流
A308: 青岛市西海岸医院 | B308: CORE | C308: 杨丽英 | D308: 神经内科 | E308: 脑血管 | F308: B | G308: 是 | H308: 否 | I308: 否 | J308: 无专诊设置 | K308: 0 | L308: 4 | M308: 4 | N308: 4 | O308: 0 | P308: 0 | Q308: 0 | R308: 0 | S308: 4 | U308: 不管不治（Freezer） | V308: 止痛优选（Repeater） | W308: 12 | X308: 观念升级，脑血管门诊，脑血管合并头痛，具备潜在患者机会 | Y308: 1、门诊拜访，重点沟通脑血管合并头痛的患者；2、用真实病例GD会议传递学术知识，建立产品认知；3、连续选用3哥患者跟进，主任收集患者使用反馈 | Z308: GD，PO会议
A309: 青岛市西海岸医院 | B309: CORE | C309: 刘丽君 | D309: 神经内科 | E309: 脑血管 | F309: B | G309: 是 | H309: 否 | I309: 否 | J309: 无专诊设置 | K309: 0 | L309: 6 | M309: 6 | N309: 0 | O309: 8 | P309: 12 | Q309: 0 | R309: 0 | S309: 4 | U309: 不管不治（Freezer） | V309: 止痛优选（Repeater） | W309: 12 | X309: 观念升级，脑血管门诊，脑血管合并头痛，具备潜在患者机会 | Y309: 1、门诊拜访，重点沟通脑血管合并头痛的患者；2、用真实病例GD会议传递学术知识，建立产品认知；3、连续选用3哥患者跟进，主任收集患者使用反馈 | Z309: GD，PO会议
A310: 青岛市西海岸医院 | B310: CORE | C310: 于俊敏 | D310: 疼痛科 | E310: 疼痛 | F310: D | G310: 是 | H310: 是 | I310: 是 | J310: 无专诊设置 | K310: 1 | L310: 6 | M310: 7 | N310: 0 | O310: 0 | P310: 0 | Q310: 0 | R310: 0 | S310: 8 | U310: 不管不治（Freezer） | V310: 止痛优选（Repeater） | W310: 12 | X310: 观念升级，MDT打造，转变诊疗观念，挖掘慢性疼痛合并头痛患者 | Y310: 1、门诊拜访，挖掘慢性疼痛合并头痛患者机会点2、与神经内科结合，开设MDT专家头痛门诊 | Z310: 三方会议覆盖，GD，区域交流
A311: 青岛市西海岸医院 | B311: CORE | C311: 寇德伟 | D311: 疼痛科 | E311: 疼痛 | F311: D | G311: 否 | H311: 否 | I311: 是 | J311: 无专诊设置 | K311: 0 | L311: 4 | M311: 4 | N311: 0 | O311: 0 | P311: 0 | Q311: 0 | R311: 0 | S311: 0 | U311: 不管不治（Freezer） | V311: 阶梯治疗（Tryer） | W311: 12 | X311: 观念升级，患者标签识别 | Y311: 1、出诊时段拜访，以阶梯治疗理念作为沟通起点；2、挑选典型劲源性头痛等头痛病例进行交流；3、寻求首次处方突破，先建立阶梯治疗认知 | Z311: GD，PO会议
A312: 青岛市西海岸医院 | B312: CORE | C312: 杨博文 | D312: 耳鼻喉科 | E312: 头晕/眩晕 | F312: C | G312: 否 | H312: 否 | I312: 是 | J312: 无专诊设置 | K312: 0 | L312: 6 | M312: 6 | N312: 0 | O312: 4 | P312: 4 | Q312: 0 | R312: 0 | S312: 0 | U312: 不管不治（Freezer） | V312: 阶梯治疗（Tryer） | W312: 12 | X312: 观念升级，患者标签，识别耳鼻喉眩晕患者同时合并头痛 | Y312: 1、门诊拜访，重点沟通耳源性眩晕，VM的识别以及用药；2、以治疗作为切入点，提供VM病例；3、筛选合适患者连续尝试使用 | Z312: GD，PO会议
A313: 青岛市西海岸医院 | B313: CORE | C313: 黄天桥 | D313: 耳鼻喉科 | E313: 头晕/眩晕 | F313: C | G313: 否 | H313: 否 | I313: 是 | J313: 无专诊设置 | K313: 0 | L313: 4 | M313: 4 | N313: 0 | O313: 0 | P313: 8 | Q313: 0 | R313: 0 | S313: 0 | U313: 不管不治（Freezer） | V313: 不管不治（Freezer） | W313: 0 | X313: * | Y313: * | Z313: *
A314: 青岛市中医医院 | B314: CORE | C314: 于永鹏 | D314: 神经内科 | E314: 头痛 | F314: A | G314: 是 | H314: 是 | I314: 是 | J314: 头痛专诊 | K314: 12 | L314: 4 | M314: 16 | N314: 112 | O314: 100 | P314: 128 | Q314: 124 | R314: 100 | U314: 短期治痛（Advocator） | V314: 治痛管理（Ambassador） | W314: 130 | X314: 治痛治晕理念较好；合作意愿度高 | Y314: PSR患者管理随访，定期反馈，病例积累制作，融动主任病例分享，搭建区域交流平台 | Z314: 三方会1
A315: 青岛市中医医院 | B315: CORE | C315: 朱晓宁 | D315: 耳鼻喉科 | E315: 头晕/眩晕 | F315: C | G315: 是 | H315: 是 | I315: 是 | J315: 无专诊设置 | K315: 0 | L315: 24 | M315: 24 | N315: 24 | O315: 28 | P315: 40 | Q315: 20 | R315: 52 | U315: 止痛优选（Repeater） | V315: 短期治痛（Advocator） | W315: 70 | X315: 眩晕学会的成立，眩晕门诊推动 | Y315: 9月底募集号委员名单，协助主任做好平台搭建，中青年圈子 | Z315: 学会资源支持，DM及市场部协防
A316: 青岛市中医医院 | B316: CORE | C316: 葛洪洲 | D316: 耳鼻喉科 | E316: 头晕/眩晕 | F316: C | G316: 是 | H316: 是 | I316: 是 | J316: 无专诊设置 | K316: 0 | L316: 24 | M316: 24 | N316: 0 | O316: 28 | P316: 28 | Q316: 24 | R316: 44 | U316: 止痛优选（Repeater） | V316: 短期治痛（Advocator） | W316: 70 | X316: 治痛治晕理念较好；推荐率、提及率较高，配合度高，话术有待提升 | Y316: 病例积累分享；提供交流平台 | Z316: 三方讨论1
A317: 青岛市中医医院 | B317: CORE | C317: 马晓维 | D317: 神经内科 | E317: 头晕/眩晕 | F317: C | G317: 是 | H317: 是 | I317: 是 | J317: 头晕/眩晕专诊 | K317: 4 | L317: 4 | M317: 8 | N317: 12 | O317: 44 | P317: 28 | Q317: 28 | R317: 20 | U317: 阶梯治疗（Tryer） | V317: 止痛优选（Repeater） | W317: 40 | X317: 每周出眩晕专诊，但患者质量及诊断需提升 | Y317: 清秀主任跟诊交流学习 | Z317: PO讨论1
A318: 青岛市中医医院 | B318: CORE | C318: 陈卫 | D318: 神经内科 | E318: 头晕/眩晕 | F318: C | G318: 是 | H318: 否 | I318: 是 | J318: 头晕/眩晕专诊 | K318: 4 | L318: 4 | M318: 8 | N318: 0 | O318: 0 | P318: 0 | Q318: 4 | R318: 12 | U318: 阶梯治疗（Tryer） | V318: 阶梯治疗（Tryer） | W318: 20 | X318: 每周出眩晕专诊，但患者质量及诊断需提升，处于尝试阶段 | Y318: 夜访融动；张甦琳教授观念影响，多与毛主任交流 | Z318: PO讨论1
A319: 青岛市中医医院 | B319: CORE | C319: 李彬 | D319: 神经内科 | E319: 脑血管 | F319: B | G319: 是 | H319: 否 | I319: 是 | J319: 无专诊设置 | K319: 0 | L319: 16 | M319: 16 | N319: 0 | O319: 0 | P319: 4 | Q319: 0 | R319: 4 | U319: 阶梯治疗（Tryer） | V319: 阶梯治疗（Tryer） | W319: 12 | X319: 科主任，对于产品较为支持，有过处方经验但不够稳定 | Y319: 科室GD会议覆盖，融动主任支持产品用药，营造学术氛围 | Z319: LB1场
A320: 青岛市中医医院 | B320: CORE | C320: 匡逸 | D320: 神经内科 | E320: 脑血管 | F320: B | G320: 是 | H320: 否 | I320: 是 | J320: 无专诊设置 | K320: 0 | L320: 2 | M320: 2 | N320: 0 | O320: 4 | P320: 4 | Q320: 4 | R320: 4 | U320: 阶梯治疗（Tryer） | V320: 阶梯治疗（Tryer） | W320: 12 | X320: 住院医师，急诊及病房积极推荐 | Y320: 客情基础较好，利用Pim持续跟进 | Z320: 暂无
A321: 青岛市中医医院 | B321: CORE | C321: 唐咏春 | D321: 神经内科 | E321: 脑血管 | F321: B | G321: 是 | H321: 否 | I321: 是 | J321: 无专诊设置 | K321: 0 | L321: 16 | M321: 16 | N321: 4 | O321: 4 | P321: 8 | Q321: 4 | R321: 4 | U321: 阶梯治疗（Tryer） | V321: 阶梯治疗（Tryer） | W321: 12 | X321: 门诊患者较少，处于尝试阶段，有处方经验且有病例正反馈 | Y321: 资源倾向性客户，通过会议提升观念 | Z321: 暂无
A322: 青岛市中医医院 | B322: CORE | C322: 牛昱光 | D322: 神经内科 | E322: 脑血管 | F322: B | G322: 是 | H322: 否 | I322: 是 | J322: 无专诊设置 | K322: 0 | L322: 8 | M322: 8 | N322: 12 | O322: 8 | P322: 4 | Q322: 4 | R322: 4 | U322: 阶梯治疗（Tryer） | V322: 止痛优选（Repeater） | W322: 40 | X322: 对头痛头晕专业方向感兴趣，融动出头痛专诊中，且有处方经验 | Y322: 需进行资源覆盖，通过大咖带动观念提升，推动进入中青年平台 | Z322: 三方讨论1
A323: 青岛市中医医院 | B323: CORE | C323: 姜明星 | D323: 耳鼻喉科 | E323: 头晕/眩晕 | F323: C | G323: 是 | H323: 否 | I323: 是 | J323: 无专诊设置 | K323: 0 | L323: 16 | M323: 16 | N323: 0 | O323: 0 | P323: 4 | Q323: 0 | R323: 0 | U323: 不管不治（Freezer） | V323: 阶梯治疗（Tryer） | W323: 12 | X323: 有破冰处方经验，但不够持续，对于眩晕方向感兴趣，后续愿意出专诊 | Y323: 推动VM画像经验积累，提供平台，中青年圈层 | Z323: 暂无
A324: 青岛市中医医院 | B324: CORE | C324: 韩萍 | D324: 神经内科 | E324: 脑血管 | F324: B | G324: 是 | H324: 否 | I324: 是 | J324: 无专诊设置 | K324: 0 | L324: 24 | M324: 24 | N324: 0 | O324: 0 | P324: 4 | Q324: 4 | R324: 0 | U324: 不管不治（Freezer） | V324: 阶梯治疗（Tryer） | W324: 0 | X324: 行政职务，对于后续产品进院提单有助力，对产品较为支持 | Y324: 持续客情维护，大客户管理 | Z324: 暂无
A325: 青岛市中医医院 | B325: CORE | C325: 陈晓宇 | D325: 耳鼻喉科 | E325: 头晕/眩晕 | F325: C | G325: 是 | H325: 是 | I325: 是 | J325: 无专诊设置 | K325: 0 | L325: 16 | M325: 16 | N325: 52 | O325: 64 | P325: 84 | Q325: 28 | R325: 0 | U325: 不管不治（Freezer） | V325: 不管不治（Freezer） | W325: 0 | X325: 具备治痛管理大师潜力 目前下乡1年 | Y325: 下乡期间保持互动，学会协助 | Z325: 暂无
... A347: 山东第二医科大学附属医院 | B347: CORE | C347: 王彬 | D347: 神经内科 | E347: 头痛 | F347: A | G347: 是 | H347: 否 | I347: 是 | J347: 头痛专诊 | K347: 8 | L347: 0 | M347: 8 | N347: 4 | O347: 24 | P347: 0 | Q347: 0 | R347: 0 | U347: 不管不治（Freezer） | V347: 阶梯治疗（Tryer） | W347: 12 | X347: 观念升级，专诊规范运营，患者画像描绘 | Y347: 1、融动门诊PSR跟诊，挖掘门诊头痛就诊患者标签；2、沟通阶梯治疗之后长期止痛优选的诊疗思路；3、提供临床病例，患者累计和管理 | Z347: 引流计划、三方会
A348: 山东第二医科大学附属医院 | B348: CORE | C348: 李一才 | D348: 神经内科 | E348: 脑血管 | F348: B | G348: 是 | H348: 否 | I348: 是 | J348: 无专诊设置 | K348: 0 | L348: 8 | M348: 8 | N348: 0 | O348: 0 | P348: 0 | Q348: 0 | R348: 0 | U348: 不管不治（Freezer） | V348: 不管不治（Freezer） | W348: 12 | X348: 观念升级，脑血管门诊，脑血管合并头痛，具备潜在患者机会 | Y348: 1、门诊拜访，重点沟通脑血管合并头痛的患者；2、用真实病例GD会议传递学术知识，建立产品认知；3、连续选用2-3例患者跟进，收集患者使用反馈
A349: 山东第二医科大学附属医院 | B349: CORE | C349: 韩国胜 | D349: 神经内科 | E349: 脑血管 | F349: B | G349: 是 | H349: 否 | I349: 是 | J349: 无专诊设置 | K349: 0 | L349: 8 | M349: 8 | N349: 0 | O349: 0 | P349: 0 | Q349: 0 | R349: 0 | U349: 不管不治（Freezer） | V349: 不管不治（Freezer） | W349: 0 | X349: 急诊神内，瑞美符合急诊对症处理的疗效 | Y349: 眩晕科联动、9月以建立客情以及传递观念为主
...
